[{"name": "AU", "zip": "32803", "created": 1323405613, "time": "23:40:13", "date": "11-12-08", "id": "4ee1912d709f03c367000049"}, {"name": "ES", "zip": "32182", "created": 1323380659, "time": "16:44:19", "date": "11-12-08", "id": "4ee12fb311fb9c7714000028"}, {"name": "ms", "zip": "90013", "created": 1323378248, "time": "16:04:08", "date": "11-12-08", "id": "4ee126484bd504321c000025"}, {"name": "JP", "zip": "45224", "created": 1323365851, "time": "12:37:31", "date": "11-12-08", "id": "4ee0f5db2ee8d0654e000029"}, {"name": "TB", "zip": "92253", "created": 1323363642, "time": "12:00:42", "date": "11-12-08", "id": "4ee0ed3aec309ebf2a000065"}, {"name": "RM", "zip": "20166", "created": 1323358009, "time": "10:26:49", "date": "11-12-08", "id": "4ee0d73911fb9c6c44000017"}]