[{"name": "lg", "zip": "70506", "created": 1317355063, "time": "23:57:43", "date": "11-09-29", "id": "4e853e37fb75283d11000074"}, {"name": "ML", "zip": "11542", "created": 1317354802, "time": "23:53:22", "date": "11-09-29", "id": "4e853d32cf436a8548000078"}, {"name": "CT", "zip": "19382", "created": 1317354473, "time": "23:47:53", "date": "11-09-29", "id": "4e853be953b2cfbd2600005d"}, {"name": "TJ", "zip": "30088", "created": 1317354443, "time": "23:47:23", "date": "11-09-29", "id": "4e853bcb8d8c37432a000083"}, {"name": "KB", "zip": "", "created": 1317354389, "time": "23:46:29", "date": "11-09-29", "id": "4e853b954bd504b53f000074"}, {"name": "EF", "zip": "46804", "created": 1317354340, "time": "23:45:40", "date": "11-09-29", "id": "4e853b64709f039f3300006f"}, {"name": "YF", "zip": "48302", "created": 1317354253, "time": "23:44:13", "date": "11-09-29", "id": "4e853b0dec309e003d000072"}, {"name": "IP", "zip": "60010", "created": 1317354237, "time": "23:43:57", "date": "11-09-29", "id": "4e853afdec309ec126000037"}, {"name": "MO", "zip": "78216", "created": 1317354179, "time": "23:42:59", "date": "11-09-29", "id": "4e853ac3fb7528b955000081"}, {"name": "jh", "zip": "48910", "created": 1317354150, "time": "23:42:30", "date": "11-09-29", "id": "4e853aa68d8c37462a00007c"}, {"name": "LW", "zip": "32068", "created": 1317354027, "time": "23:40:27", "date": "11-09-29", "id": "4e853a2b11fb9c9c30000064"}, {"name": "IW", "zip": "77354", "created": 1317353758, "time": "23:35:58", "date": "11-09-29", "id": "4e85391eb256360049000073"}, {"name": "AM", "zip": "76137", "created": 1317353640, "time": "23:34:00", "date": "11-09-29", "id": "4e8538a8ec309e003d000070"}, {"name": "DT", "zip": "", "created": 1317353638, "time": "23:33:58", "date": "11-09-29", "id": "4e8538a68d8c37442a000075"}, {"name": "ER", "zip": "75002", "created": 1317353509, "time": "23:31:49", "date": "11-09-29", "id": "4e853825ec309efa3c000069"}, {"name": "JL", "zip": "37212", "created": 1317353273, "time": "23:27:53", "date": "11-09-29", "id": "4e853739cf436a854800006d"}, {"name": "AM", "zip": "02421", "created": 1317353213, "time": "23:26:53", "date": "11-09-29", "id": "4e8536fdec309efc3c000074"}, {"name": "AB", "zip": "95472", "created": 1317352990, "time": "23:23:10", "date": "11-09-29", "id": "4e85361e8d8c373f2a000078"}, {"name": "MB", "zip": "03743", "created": 1317352907, "time": "23:21:47", "date": "11-09-29", "id": "4e8535cb8d8c37402a000089"}, {"name": "VS", "zip": "48324", "created": 1317352707, "time": "23:18:27", "date": "11-09-29", "id": "4e853503709f038a6400005e"}, {"name": "RF", "zip": "80014", "created": 1317352598, "time": "23:16:38", "date": "11-09-29", "id": "4e853496b25636fc4800006b"}, {"name": "NN", "zip": "02026", "created": 1317352353, "time": "23:12:33", "date": "11-09-29", "id": "4e8533a19cd1c11d6e000063"}, {"name": "MW", "zip": "12180", "created": 1317352282, "time": "23:11:22", "date": "11-09-29", "id": "4e85335a9cd1c1a97500005f"}, {"name": "JY", "zip": "48135", "created": 1317352150, "time": "23:09:10", "date": "11-09-29", "id": "4e8532d69cd1c1bf75000051"}, {"name": "CT", "zip": "76201", "created": 1317352066, "time": "23:07:46", "date": "11-09-29", "id": "4e853282cf436a8148000067"}, {"name": "AM", "zip": "36832", "created": 1317351961, "time": "23:06:01", "date": "11-09-29", "id": "4e85321911fb9c8f30000069"}, {"name": "HB", "zip": "43360", "created": 1317351896, "time": "23:04:56", "date": "11-09-29", "id": "4e8531d8cf436a7d4800004a"}, {"name": "AS", "zip": "83401", "created": 1317351622, "time": "23:00:22", "date": "11-09-29", "id": "4e8530c62ee8d0602d000077"}, {"name": "AR", "zip": "76201", "created": 1317351465, "time": "22:57:45", "date": "11-09-29", "id": "4e85302953b2cf8d6b000065"}, {"name": "VU", "zip": "03062", "created": 1317351443, "time": "22:57:23", "date": "11-09-29", "id": "4e8530139cd1c1a97500005a"}, {"name": "SC", "zip": "", "created": 1317351367, "time": "22:56:07", "date": "11-09-29", "id": "4e852fc753b2cf1d78000051"}, {"name": "CR", "zip": "85119", "created": 1317351363, "time": "22:56:03", "date": "11-09-29", "id": "4e852fc34bd504b83f000067"}, {"name": "JB", "zip": "63119", "created": 1317351284, "time": "22:54:44", "date": "11-09-29", "id": "4e852f74ec309efb3c000051"}, {"name": "AS", "zip": "20740", "created": 1317351284, "time": "22:54:44", "date": "11-09-29", "id": "4e852f74cf436a8348000052"}, {"name": "AN", "zip": "38506", "created": 1317351112, "time": "22:51:52", "date": "11-09-29", "id": "4e852ec88d8c37132b00005c"}, {"name": "BF", "zip": "95817", "created": 1317350985, "time": "22:49:45", "date": "11-09-29", "id": "4e852e499cd1c11f6e00006e"}, {"name": "GM", "zip": "70094", "created": 1317350807, "time": "22:46:47", "date": "11-09-29", "id": "4e852d97709f03a833000060"}, {"name": "MA", "zip": "44026", "created": 1317350765, "time": "22:46:05", "date": "11-09-29", "id": "4e852d6d2ee8d0be23000031"}, {"name": "AM", "zip": "90007", "created": 1317350633, "time": "22:43:53", "date": "11-09-29", "id": "4e852ce9b25636004900005d"}, {"name": "CY", "zip": "55105", "created": 1317350580, "time": "22:43:00", "date": "11-09-29", "id": "4e852cb4b25636004900005b"}, {"name": "SS", "zip": "44710", "created": 1317350569, "time": "22:42:49", "date": "11-09-29", "id": "4e852ca92ee8d0155800005a"}, {"name": "SB", "zip": "80134", "created": 1317350520, "time": "22:42:00", "date": "11-09-29", "id": "4e852c784bd504b83f000061"}, {"name": "LM", "zip": "60044", "created": 1317350277, "time": "22:37:57", "date": "11-09-29", "id": "4e852b859cd1c11a6e000057"}, {"name": "RB", "zip": "43403", "created": 1317349823, "time": "22:30:23", "date": "11-09-29", "id": "4e8529bf709f039f33000053"}, {"name": "MO", "zip": "", "created": 1317349774, "time": "22:29:34", "date": "11-09-29", "id": "4e85298e4bd5046e41000064"}, {"name": "RS", "zip": "85286", "created": 1317349695, "time": "22:28:15", "date": "11-09-29", "id": "4e85293ffb7528b15500005c"}, {"name": "SB", "zip": "55105", "created": 1317349394, "time": "22:23:14", "date": "11-09-29", "id": "4e852812fb7528b955000073"}, {"name": "BB", "zip": "14610", "created": 1317349345, "time": "22:22:25", "date": "11-09-29", "id": "4e8527e1709f03a133000054"}, {"name": "SL", "zip": "28518", "created": 1317349301, "time": "22:21:41", "date": "11-09-29", "id": "4e8527b553b2cf1d78000048"}, {"name": "BS", "zip": "29445", "created": 1317349200, "time": "22:20:00", "date": "11-09-29", "id": "4e8527509cd1c11e6e000048"}, {"name": "MH", "zip": "22807", "created": 1317349181, "time": "22:19:41", "date": "11-09-29", "id": "4e85273d2ee8d0602d00006d"}, {"name": "JG", "zip": "", "created": 1317349126, "time": "22:18:46", "date": "11-09-29", "id": "4e8527064bd504b53f000053"}, {"name": "RF", "zip": "02828", "created": 1317349109, "time": "22:18:29", "date": "11-09-29", "id": "4e8526f553b2cf8e6b000053"}, {"name": "KL", "zip": "95112", "created": 1317348846, "time": "22:14:06", "date": "11-09-29", "id": "4e8525ee11fb9c903000005a"}, {"name": "MS", "zip": "55124", "created": 1317348501, "time": "22:08:21", "date": "11-09-29", "id": "4e852495cf436a8148000054"}, {"name": "GM", "zip": "98103", "created": 1317348431, "time": "22:07:11", "date": "11-09-29", "id": "4e85244fec309efc3c000058"}, {"name": "Pm", "zip": "06880", "created": 1317348279, "time": "22:04:39", "date": "11-09-29", "id": "4e8523b74bd504bc3f000042"}, {"name": "NB", "zip": "92054", "created": 1317348240, "time": "22:04:00", "date": "11-09-29", "id": "4e8523902ee8d0612d00004f"}, {"name": "TC", "zip": "31312", "created": 1317348135, "time": "22:02:15", "date": "11-09-29", "id": "4e8523272ee8d0e52e000053"}, {"name": "ZS", "zip": "60612", "created": 1317348135, "time": "22:02:15", "date": "11-09-29", "id": "4e85232711fb9c933000005f"}, {"name": "MB", "zip": "97205", "created": 1317348133, "time": "22:02:13", "date": "11-09-29", "id": "4e852325cf436a8248000042"}, {"name": "SG", "zip": "19504", "created": 1317348091, "time": "22:01:31", "date": "11-09-29", "id": "4e8522fbfb7528b95500006b"}, {"name": "WC", "zip": "60004-2731", "created": 1317347828, "time": "21:57:08", "date": "11-09-29", "id": "4e8521f4cf436a7d48000034"}, {"name": "OF", "zip": "22312", "created": 1317347799, "time": "21:56:39", "date": "11-09-29", "id": "4e8521d7fb7528b05500005c"}, {"name": "SB", "zip": "53073", "created": 1317347722, "time": "21:55:22", "date": "11-09-29", "id": "4e85218acf436a854800003e"}, {"name": "BP", "zip": "94040", "created": 1317347692, "time": "21:54:52", "date": "11-09-29", "id": "4e85216c709f039d3300005f"}, {"name": "PW", "zip": "84103", "created": 1317347617, "time": "21:53:37", "date": "11-09-29", "id": "4e8521219cd1c11b6e000042"}, {"name": "TM", "zip": "20120", "created": 1317347609, "time": "21:53:29", "date": "11-09-29", "id": "4e852119cf436a854800003d"}, {"name": "LW", "zip": "60046", "created": 1317347525, "time": "21:52:05", "date": "11-09-29", "id": "4e8520c5b25636ca6100002c"}, {"name": "JM", "zip": "10029", "created": 1317347508, "time": "21:51:48", "date": "11-09-29", "id": "4e8520b411fb9c011b000023"}, {"name": "ER", "zip": "43022", "created": 1317347314, "time": "21:48:34", "date": "11-09-29", "id": "4e851ff29cd1c1bf7500003a"}, {"name": "MS", "zip": "99506", "created": 1317347006, "time": "21:43:26", "date": "11-09-29", "id": "4e851ebe2ee8d05a2d000052"}, {"name": "ML", "zip": "11561", "created": 1317346868, "time": "21:41:08", "date": "11-09-29", "id": "4e851e34cf436a7e4800003a"}, {"name": "Jv", "zip": "96129", "created": 1317346841, "time": "21:40:41", "date": "11-09-29", "id": "4e851e199cd1c1206e00004c"}, {"name": "JL", "zip": "94305", "created": 1317346622, "time": "21:37:02", "date": "11-09-29", "id": "4e851d3e2ee8d01558000042"}, {"name": "ES", "zip": "21040", "created": 1317346617, "time": "21:36:57", "date": "11-09-29", "id": "4e851d399cd1c11d6e000036"}, {"name": "ST", "zip": "96816", "created": 1317346392, "time": "21:33:12", "date": "11-09-29", "id": "4e851c58fb7528b95500005d"}, {"name": "WJ", "zip": "82833", "created": 1317346364, "time": "21:32:44", "date": "11-09-29", "id": "4e851c3c4bd504b73f000048"}, {"name": "BB", "zip": "64086", "created": 1317346284, "time": "21:31:24", "date": "11-09-29", "id": "4e851bec2ee8d01558000041"}, {"name": "tt", "zip": "54935", "created": 1317346225, "time": "21:30:25", "date": "11-09-29", "id": "4e851bb14bd504b93f000046"}, {"name": "RC", "zip": "18102", "created": 1317346135, "time": "21:28:55", "date": "11-09-29", "id": "4e851b57cf436a9548000042"}, {"name": "RT", "zip": "94043", "created": 1317345961, "time": "21:26:01", "date": "11-09-29", "id": "4e851aa9fb7528b65500003f"}, {"name": "SB", "zip": "98007", "created": 1317345873, "time": "21:24:33", "date": "11-09-29", "id": "4e851a512ee8d05e2d000038"}, {"name": "CG", "zip": "77840", "created": 1317345819, "time": "21:23:39", "date": "11-09-29", "id": "4e851a1b8d8c37c367000032"}, {"name": "JP", "zip": "59808", "created": 1317345742, "time": "21:22:22", "date": "11-09-29", "id": "4e8519ce8d8c37432a00005e"}, {"name": "BW", "zip": "17538", "created": 1317345689, "time": "21:21:29", "date": "11-09-29", "id": "4e8519999cd1c1be75000035"}, {"name": "MS", "zip": "84112", "created": 1317345615, "time": "21:20:15", "date": "11-09-29", "id": "4e85194fb256363c2500001a"}, {"name": "JF", "zip": "78666", "created": 1317345443, "time": "21:17:23", "date": "11-09-29", "id": "4e8518a3b25636f448000040"}, {"name": "PW", "zip": "98032", "created": 1317345280, "time": "21:14:40", "date": "11-09-29", "id": "4e85180011fb9c9030000044"}, {"name": "RJ", "zip": "32792", "created": 1317345078, "time": "21:11:18", "date": "11-09-29", "id": "4e8517369cd1c1bf75000030"}, {"name": "EE", "zip": "75062", "created": 1317344981, "time": "21:09:41", "date": "11-09-29", "id": "4e8516d5fb7528b655000034"}, {"name": "AB", "zip": "63031", "created": 1317344939, "time": "21:08:59", "date": "11-09-29", "id": "4e8516ab9cd1c1bf7500002e"}, {"name": "Al", "zip": "01830", "created": 1317344859, "time": "21:07:39", "date": "11-09-29", "id": "4e85165bfb7528b855000032"}, {"name": "BD", "zip": "85258", "created": 1317344639, "time": "21:03:59", "date": "11-09-29", "id": "4e85157fec309e3b6e00001d"}, {"name": "RB", "zip": "91745", "created": 1317344621, "time": "21:03:41", "date": "11-09-29", "id": "4e85156dec309efe3c00003d"}, {"name": "KP", "zip": "30656", "created": 1317344467, "time": "21:01:07", "date": "11-09-29", "id": "4e8514d32ee8d0155800002c"}, {"name": "NE", "zip": "93308", "created": 1317344381, "time": "20:59:41", "date": "11-09-29", "id": "4e85147d8d8c373f2a000049"}, {"name": "JA", "zip": "48108", "created": 1317344349, "time": "20:59:09", "date": "11-09-29", "id": "4e85145d4bd504bd3f000034"}, {"name": "AA", "zip": "91745", "created": 1317344141, "time": "20:55:41", "date": "11-09-29", "id": "4e85138dfb7528e22200001b"}, {"name": "JN", "zip": "03060", "created": 1317344087, "time": "20:54:47", "date": "11-09-29", "id": "4e851357b25636ff48000034"}, {"name": "LE", "zip": "41073", "created": 1317343998, "time": "20:53:18", "date": "11-09-29", "id": "4e8512fe709f032434000036"}, {"name": "HC", "zip": "02382", "created": 1317343956, "time": "20:52:36", "date": "11-09-29", "id": "4e8512d4cf436a7d4800001f"}, {"name": "cH", "zip": "55405", "created": 1317343940, "time": "20:52:20", "date": "11-09-29", "id": "4e8512c4cf436a8548000028"}, {"name": "JP", "zip": "15102", "created": 1317343886, "time": "20:51:26", "date": "11-09-29", "id": "4e85128e709f039d3300003f"}, {"name": "BG", "zip": "22602", "created": 1317343681, "time": "20:48:01", "date": "11-09-29", "id": "4e8511c1fb7528b95500003a"}, {"name": "CK", "zip": "92081", "created": 1317343636, "time": "20:47:16", "date": "11-09-29", "id": "4e8511944bd504be3f00003b"}, {"name": "KP", "zip": "30024", "created": 1317343608, "time": "20:46:48", "date": "11-09-29", "id": "4e851178cf436a8348000028"}, {"name": "pl", "zip": "98112", "created": 1317343535, "time": "20:45:35", "date": "11-09-29", "id": "4e85112f709f038a6400001e"}, {"name": "CM", "zip": "28443", "created": 1317343192, "time": "20:39:52", "date": "11-09-29", "id": "4e850fd88d8c37452a00003e"}, {"name": "SE", "zip": "98110", "created": 1317343169, "time": "20:39:29", "date": "11-09-29", "id": "4e850fc1fb7528af5500003a"}, {"name": "LH", "zip": "64109", "created": 1317343167, "time": "20:39:27", "date": "11-09-29", "id": "4e850fbfb25636ca61000013"}, {"name": "AK", "zip": "48071", "created": 1317343066, "time": "20:37:46", "date": "11-09-29", "id": "4e850f5a9cd1c11a6e000028"}, {"name": "TC", "zip": "", "created": 1317342909, "time": "20:35:09", "date": "11-09-29", "id": "4e850ebd2ee8d0155800001c"}, {"name": "KR", "zip": "46962", "created": 1317342751, "time": "20:32:31", "date": "11-09-29", "id": "4e850e1ffb7528ae55000034"}, {"name": "BL", "zip": "19149", "created": 1317342589, "time": "20:29:49", "date": "11-09-29", "id": "4e850d7dec309efa3c000035"}, {"name": "PP", "zip": "20132", "created": 1317342579, "time": "20:29:39", "date": "11-09-29", "id": "4e850d7311fb9c9830000030"}, {"name": "DH", "zip": "38358", "created": 1317342523, "time": "20:28:43", "date": "11-09-29", "id": "4e850d3bfb7528b055000037"}, {"name": "SC", "zip": "32765", "created": 1317342486, "time": "20:28:06", "date": "11-09-29", "id": "4e850d169cd1c1206e000033"}, {"name": "SM", "zip": "55414", "created": 1317342402, "time": "20:26:42", "date": "11-09-29", "id": "4e850cc2b25636fc48000021"}, {"name": "lb", "zip": "28905", "created": 1317342014, "time": "20:20:14", "date": "11-09-29", "id": "4e850b3e53b2cf8d6b000020"}, {"name": "CB", "zip": "44515", "created": 1317341969, "time": "20:19:29", "date": "11-09-29", "id": "4e850b1111fb9c9230000028"}, {"name": "JT", "zip": "37145", "created": 1317341516, "time": "20:11:56", "date": "11-09-29", "id": "4e85094c8d8c37c36700000f"}, {"name": "NV", "zip": "99801", "created": 1317341506, "time": "20:11:46", "date": "11-09-29", "id": "4e850942709f03a03300001e"}, {"name": "cs", "zip": "06249", "created": 1317341358, "time": "20:09:18", "date": "11-09-29", "id": "4e8508aecf436a7e4800001e"}, {"name": "KW", "zip": "20676", "created": 1317341343, "time": "20:09:03", "date": "11-09-29", "id": "4e85089f9cd1c11f6e000028"}, {"name": "bh", "zip": "44129", "created": 1317341316, "time": "20:08:36", "date": "11-09-29", "id": "4e850884ec309efe3c00002a"}, {"name": "ZK", "zip": "98012", "created": 1317341261, "time": "20:07:41", "date": "11-09-29", "id": "4e85084d709f039f3300001b"}, {"name": "JD", "zip": "81082", "created": 1317341079, "time": "20:04:39", "date": "11-09-29", "id": "4e850797b25636fa4800001a"}, {"name": "MM", "zip": "90067", "created": 1317340701, "time": "19:58:21", "date": "11-09-29", "id": "4e85061dfb75283d1100000e"}, {"name": "BC", "zip": "85045", "created": 1317340635, "time": "19:57:15", "date": "11-09-29", "id": "4e8505db4bd504be3f00001e"}, {"name": "MW", "zip": "95003", "created": 1317340545, "time": "19:55:45", "date": "11-09-29", "id": "4e850581ec309efa3c00001f"}, {"name": "LK", "zip": "", "created": 1317340444, "time": "19:54:04", "date": "11-09-29", "id": "4e85051c8d8c37412a000039"}, {"name": "JB", "zip": "15714", "created": 1317340372, "time": "19:52:52", "date": "11-09-29", "id": "4e8504d453b2cf8d6b000016"}, {"name": "LC", "zip": "21532", "created": 1317340127, "time": "19:48:47", "date": "11-09-29", "id": "4e8503dfec309efe3c00001d"}, {"name": "LT", "zip": "74105", "created": 1317340055, "time": "19:47:35", "date": "11-09-29", "id": "4e85039753b2cf8d6b000012"}, {"name": "GV", "zip": "75007", "created": 1317339782, "time": "19:43:02", "date": "11-09-29", "id": "4e850286cf436a8548000010"}, {"name": "FD", "zip": "23518", "created": 1317339675, "time": "19:41:15", "date": "11-09-29", "id": "4e85021b709f03a83300001a"}, {"name": "LP", "zip": "38570", "created": 1317339546, "time": "19:39:06", "date": "11-09-29", "id": "4e85019a53b2cf3313000002"}, {"name": "JS", "zip": "78753", "created": 1317339524, "time": "19:38:44", "date": "11-09-29", "id": "4e850184709f03a73300001a"}, {"name": "ZA", "zip": "47401", "created": 1317339477, "time": "19:37:57", "date": "11-09-29", "id": "4e850155cf436a8148000019"}, {"name": "NK", "zip": "13502", "created": 1317339096, "time": "19:31:36", "date": "11-09-29", "id": "4e84ffd811fb9c8f30000016"}, {"name": "LH", "zip": "95370", "created": 1317339032, "time": "19:30:32", "date": "11-09-29", "id": "4e84ff9853b2cf8e6b00001e"}, {"name": "RH", "zip": "94589", "created": 1317338866, "time": "19:27:46", "date": "11-09-29", "id": "4e84fef253b2cf8b6b000013"}, {"name": "SH", "zip": "94589", "created": 1317338827, "time": "19:27:07", "date": "11-09-29", "id": "4e84fecb4bd504b83f000015"}, {"name": "KA", "zip": "27615", "created": 1317338796, "time": "19:26:36", "date": "11-09-29", "id": "4e84feac2ee8d05b2d000018"}, {"name": "KB", "zip": "10708", "created": 1317338687, "time": "19:24:47", "date": "11-09-29", "id": "4e84fe3fec309efe3c000011"}, {"name": "cb", "zip": "92868", "created": 1317338683, "time": "19:24:43", "date": "11-09-29", "id": "4e84fe3bfb7528b055000020"}, {"name": "JG", "zip": "14782", "created": 1317338603, "time": "19:23:23", "date": "11-09-29", "id": "4e84fdebfb7528b65500001b"}, {"name": "KB", "zip": "38505", "created": 1317338540, "time": "19:22:20", "date": "11-09-29", "id": "4e84fdacb25636fa48000006"}, {"name": "dh", "zip": "77808", "created": 1317338479, "time": "19:21:19", "date": "11-09-29", "id": "4e84fd6f8d8c37412a000027"}, {"name": "Js", "zip": "", "created": 1317338174, "time": "19:16:14", "date": "11-09-29", "id": "4e84fc3eec309efc3c000014"}, {"name": "KJ", "zip": "92264", "created": 1317338173, "time": "19:16:13", "date": "11-09-29", "id": "4e84fc3dec309efe3c00000f"}, {"name": "AS", "zip": "60657-2626", "created": 1317338053, "time": "19:14:13", "date": "11-09-29", "id": "4e84fbc5fb7528af55000018"}, {"name": "TW", "zip": "92603", "created": 1317337666, "time": "19:07:46", "date": "11-09-29", "id": "4e84fa428d8c37452a000016"}, {"name": "EG", "zip": "92234", "created": 1317337587, "time": "19:06:27", "date": "11-09-29", "id": "4e84f9f38d8c37412a00001b"}, {"name": "MS", "zip": "92019", "created": 1317337475, "time": "19:04:35", "date": "11-09-29", "id": "4e84f983cf436a8348000005"}, {"name": "CD", "zip": "53706", "created": 1317337420, "time": "19:03:40", "date": "11-09-29", "id": "4e84f94ccf436a7d48000003"}, {"name": "GL", "zip": "33609", "created": 1317337412, "time": "19:03:32", "date": "11-09-29", "id": "4e84f94453b2cf8e6b00000e"}, {"name": "JM", "zip": "87112", "created": 1317337001, "time": "18:56:41", "date": "11-09-29", "id": "4e84f7a94bd504b73f000010"}, {"name": "TL", "zip": "92262", "created": 1317336972, "time": "18:56:12", "date": "11-09-29", "id": "4e84f78c9cd1c11b6e000001"}, {"name": "CC", "zip": "21236", "created": 1317336795, "time": "18:53:15", "date": "11-09-29", "id": "4e84f6db4bd504bc3f000007"}, {"name": "RG", "zip": "94565", "created": 1317336780, "time": "18:53:00", "date": "11-09-29", "id": "4e84f6ccb256363f49000000"}, {"name": "kd", "zip": "18337", "created": 1317336779, "time": "18:52:59", "date": "11-09-29", "id": "4e84f6cbec309efb3c00000c"}, {"name": "SD", "zip": "15601", "created": 1317336706, "time": "18:51:46", "date": "11-09-29", "id": "4e84f682709f03d23a000000"}, {"name": "SL", "zip": "08648", "created": 1317336466, "time": "18:47:46", "date": "11-09-29", "id": "4e84f5922ee8d0e52e000008"}, {"name": "LZ", "zip": "30033", "created": 1317336435, "time": "18:47:15", "date": "11-09-29", "id": "4e84f573ec309e013d000004"}, {"name": "CR", "zip": "", "created": 1317336258, "time": "18:44:18", "date": "11-09-29", "id": "4e84f4c2cf436aa80a000077"}, {"name": "DG", "zip": "", "created": 1317335877, "time": "18:37:57", "date": "11-09-29", "id": "4e84f34553b2cf150700006b"}, {"name": "CB", "zip": "44023", "created": 1317335792, "time": "18:36:32", "date": "11-09-29", "id": "4e84f2f09cd1c1ce0900006b"}, {"name": "SO", "zip": "77024", "created": 1317335780, "time": "18:36:20", "date": "11-09-29", "id": "4e84f2e453b2cf1607000071"}, {"name": "DD", "zip": "80751", "created": 1317335626, "time": "18:33:46", "date": "11-09-29", "id": "4e84f24a709f030f7800001d"}, {"name": "SR", "zip": "86327", "created": 1317335625, "time": "18:33:45", "date": "11-09-29", "id": "4e84f2492ee8d05c2d000000"}, {"name": "lb", "zip": "94925", "created": 1317335418, "time": "18:30:18", "date": "11-09-29", "id": "4e84f17a11fb9cd50f000063"}, {"name": "GC", "zip": "", "created": 1317335348, "time": "18:29:08", "date": "11-09-29", "id": "4e84f134cf436ad47f000014"}, {"name": "BT", "zip": "33613", "created": 1317335314, "time": "18:28:34", "date": "11-09-29", "id": "4e84f112cf436ad97f000021"}, {"name": "JS", "zip": "47501", "created": 1317335164, "time": "18:26:04", "date": "11-09-29", "id": "4e84f07c2ee8d05a17000069"}, {"name": "DF", "zip": "77546", "created": 1317335158, "time": "18:25:58", "date": "11-09-29", "id": "4e84f0768d8c37422a000005"}, {"name": "MH", "zip": "03820", "created": 1317335141, "time": "18:25:41", "date": "11-09-29", "id": "4e84f06511fb9c9e75000025"}, {"name": "SA", "zip": "50315", "created": 1317335001, "time": "18:23:21", "date": "11-09-29", "id": "4e84efd953b2cf1307000086"}, {"name": "TK", "zip": "44106", "created": 1317334756, "time": "18:19:16", "date": "11-09-29", "id": "4e84eee4cf436aa80a000070"}, {"name": "RG", "zip": "11516", "created": 1317334658, "time": "18:17:38", "date": "11-09-29", "id": "4e84ee829cd1c1bf09000072"}, {"name": "RN", "zip": "63026", "created": 1317334369, "time": "18:12:49", "date": "11-09-29", "id": "4e84ed619cd1c1ce09000068"}, {"name": "RC", "zip": "11741", "created": 1317334351, "time": "18:12:31", "date": "11-09-29", "id": "4e84ed4f53b2cfaf37000015"}, {"name": "FW", "zip": "98503", "created": 1317334295, "time": "18:11:35", "date": "11-09-29", "id": "4e84ed17cf436ad37f00001a"}, {"name": "BB", "zip": "71913", "created": 1317334124, "time": "18:08:44", "date": "11-09-29", "id": "4e84ec6c9cd1c1a509000051"}, {"name": "KK", "zip": "78726", "created": 1317334038, "time": "18:07:18", "date": "11-09-29", "id": "4e84ec16fb7528580c000072"}, {"name": "JF", "zip": "91403", "created": 1317334022, "time": "18:07:02", "date": "11-09-29", "id": "4e84ec0653b2cf070700006e"}, {"name": "RB", "zip": "76023", "created": 1317333982, "time": "18:06:22", "date": "11-09-29", "id": "4e84ebde2ee8d0bb74000017"}, {"name": "LA", "zip": "92064", "created": 1317333963, "time": "18:06:03", "date": "11-09-29", "id": "4e84ebcbec309e7b1b000055"}, {"name": "DF", "zip": "72801", "created": 1317333738, "time": "18:02:18", "date": "11-09-29", "id": "4e84eaeaec309e2403000019"}, {"name": "JH", "zip": "99163", "created": 1317333522, "time": "17:58:42", "date": "11-09-29", "id": "4e84ea12cf436ada7f00001f"}, {"name": "KM", "zip": "46616", "created": 1317333506, "time": "17:58:26", "date": "11-09-29", "id": "4e84ea0253b2cf1a07000072"}, {"name": "SM", "zip": "32809", "created": 1317333423, "time": "17:57:03", "date": "11-09-29", "id": "4e84e9af4bd504111d00006d"}, {"name": "CF", "zip": "76205", "created": 1317333393, "time": "17:56:33", "date": "11-09-29", "id": "4e84e9918d8c375615000050"}, {"name": "JB", "zip": "73072", "created": 1317333155, "time": "17:52:35", "date": "11-09-29", "id": "4e84e8a32ee8d0b47400001c"}, {"name": "RH", "zip": "78526", "created": 1317333154, "time": "17:52:34", "date": "11-09-29", "id": "4e84e8a22ee8d04317000073"}, {"name": "PC", "zip": "77381", "created": 1317333100, "time": "17:51:40", "date": "11-09-29", "id": "4e84e86cec309e6b1b000076"}, {"name": "eg", "zip": "", "created": 1317332961, "time": "17:49:21", "date": "11-09-29", "id": "4e84e7e153b2cfc237000019"}, {"name": "BP", "zip": "60630", "created": 1317332928, "time": "17:48:48", "date": "11-09-29", "id": "4e84e7c04bd5041d2700005b"}, {"name": "MR", "zip": "59801", "created": 1317332849, "time": "17:47:29", "date": "11-09-29", "id": "4e84e771b25636bc01000021"}, {"name": "KH", "zip": "67330", "created": 1317332812, "time": "17:46:52", "date": "11-09-29", "id": "4e84e74c709f03197800000d"}, {"name": "JH", "zip": "97124", "created": 1317332742, "time": "17:45:42", "date": "11-09-29", "id": "4e84e706fb75285a0c00006d"}, {"name": "JD", "zip": "43402", "created": 1317332731, "time": "17:45:31", "date": "11-09-29", "id": "4e84e6fb709f03d51b000077"}, {"name": "MF", "zip": "02915", "created": 1317332725, "time": "17:45:25", "date": "11-09-29", "id": "4e84e6f5ec309e1f0300001b"}, {"name": "RJ", "zip": "14075", "created": 1317332662, "time": "17:44:22", "date": "11-09-29", "id": "4e84e6b6fb7528580c000065"}, {"name": "PM", "zip": "94131", "created": 1317332616, "time": "17:43:36", "date": "11-09-29", "id": "4e84e6888d8c37e77b000019"}, {"name": "DC", "zip": "95901", "created": 1317332605, "time": "17:43:25", "date": "11-09-29", "id": "4e84e67d709f03ba1b000064"}, {"name": "JL", "zip": "63026", "created": 1317332594, "time": "17:43:14", "date": "11-09-29", "id": "4e84e672b256369a0a00005b"}, {"name": "AS", "zip": "49202", "created": 1317332401, "time": "17:40:01", "date": "11-09-29", "id": "4e84e5b1fb7528560c000075"}, {"name": "JG", "zip": "97045", "created": 1317332345, "time": "17:39:05", "date": "11-09-29", "id": "4e84e579b256369b0a000070"}, {"name": "MB", "zip": "97222", "created": 1317332193, "time": "17:36:33", "date": "11-09-29", "id": "4e84e4e1b25636b70a000062"}, {"name": "jh", "zip": "50010", "created": 1317332123, "time": "17:35:23", "date": "11-09-29", "id": "4e84e49bcf436ad37f000015"}, {"name": "DC", "zip": "84094", "created": 1317332065, "time": "17:34:25", "date": "11-09-29", "id": "4e84e461ec309e961b000061"}, {"name": "JM", "zip": "59715", "created": 1317331934, "time": "17:32:14", "date": "11-09-29", "id": "4e84e3de53b2cfb63700001c"}, {"name": "JB", "zip": "97702", "created": 1317331634, "time": "17:27:14", "date": "11-09-29", "id": "4e84e2b28d8c37c67b00001e"}, {"name": "SD", "zip": "02072", "created": 1317331601, "time": "17:26:41", "date": "11-09-29", "id": "4e84e29111fb9c651c000052"}, {"name": "MS", "zip": "21703", "created": 1317331440, "time": "17:24:00", "date": "11-09-29", "id": "4e84e1f011fb9c8e10000076"}, {"name": "KK", "zip": "43202", "created": 1317331387, "time": "17:23:07", "date": "11-09-29", "id": "4e84e1bbfb7528510c000069"}, {"name": "BM", "zip": "70554", "created": 1317331275, "time": "17:21:15", "date": "11-09-29", "id": "4e84e14b53b2cf060700006a"}, {"name": "DJ", "zip": "63376", "created": 1317331050, "time": "17:17:30", "date": "11-09-29", "id": "4e84e06a53b2cfd719000059"}, {"name": "RA", "zip": "78705", "created": 1317330939, "time": "17:15:39", "date": "11-09-29", "id": "4e84dffb9cd1c1c809000068"}, {"name": "TG", "zip": "", "created": 1317330810, "time": "17:13:30", "date": "11-09-29", "id": "4e84df7a709f039d1b000059"}, {"name": "EB", "zip": "11565", "created": 1317330554, "time": "17:09:14", "date": "11-09-29", "id": "4e84de7a8d8c375115000048"}, {"name": "RB", "zip": "08043", "created": 1317330536, "time": "17:08:56", "date": "11-09-29", "id": "4e84de682ee8d06117000058"}, {"name": "TS", "zip": "97219", "created": 1317330447, "time": "17:07:27", "date": "11-09-29", "id": "4e84de0f8d8c375215000062"}, {"name": "mG", "zip": "36117", "created": 1317330401, "time": "17:06:41", "date": "11-09-29", "id": "4e84dde1cf436a521f000047"}, {"name": "JJ", "zip": "63376", "created": 1317330376, "time": "17:06:16", "date": "11-09-29", "id": "4e84ddc8ec309e5a1b000069"}, {"name": "ZF", "zip": "80203", "created": 1317330365, "time": "17:06:05", "date": "11-09-29", "id": "4e84ddbd709f03d41b000065"}, {"name": "CH", "zip": "", "created": 1317330301, "time": "17:05:01", "date": "11-09-29", "id": "4e84dd7d4bd504e60700000e"}, {"name": "JB", "zip": "44485", "created": 1317329831, "time": "16:57:11", "date": "11-09-29", "id": "4e84dba7cf436ae37f000013"}, {"name": "HL", "zip": "75093", "created": 1317329819, "time": "16:56:59", "date": "11-09-29", "id": "4e84db9bcf436af609000070"}, {"name": "JS", "zip": "30082", "created": 1317329746, "time": "16:55:46", "date": "11-09-29", "id": "4e84db52cf436afa09000054"}, {"name": "ML", "zip": "04102", "created": 1317329589, "time": "16:53:09", "date": "11-09-29", "id": "4e84dab5b25636c50100000e"}, {"name": "CB", "zip": "", "created": 1317329442, "time": "16:50:42", "date": "11-09-29", "id": "4e84da228d8c375315000058"}, {"name": "AC", "zip": "68104", "created": 1317329429, "time": "16:50:29", "date": "11-09-29", "id": "4e84da15b256369b0a000060"}, {"name": "DR", "zip": "10601", "created": 1317329366, "time": "16:49:26", "date": "11-09-29", "id": "4e84d9d6b25636b201000012"}, {"name": "TD", "zip": "454503", "created": 1317329333, "time": "16:48:53", "date": "11-09-29", "id": "4e84d9b5b256368d0a00006d"}, {"name": "DE", "zip": "02127", "created": 1317329014, "time": "16:43:34", "date": "11-09-29", "id": "4e84d876fb75284d0c00005c"}, {"name": "MP", "zip": "92101", "created": 1317328757, "time": "16:39:17", "date": "11-09-29", "id": "4e84d77511fb9cd30f00006b"}, {"name": "WB", "zip": "", "created": 1317328629, "time": "16:37:09", "date": "11-09-29", "id": "4e84d6f5709f039d1b000055"}, {"name": "FC", "zip": "92562", "created": 1317328589, "time": "16:36:29", "date": "11-09-29", "id": "4e84d6cdb25636b201000011"}, {"name": "EA", "zip": "98117", "created": 1317328393, "time": "16:33:13", "date": "11-09-29", "id": "4e84d609709f03c71b000055"}, {"name": "KF", "zip": "21146", "created": 1317328150, "time": "16:29:10", "date": "11-09-29", "id": "4e84d5164bd504e70700000f"}, {"name": "MS", "zip": "07481", "created": 1317328140, "time": "16:29:00", "date": "11-09-29", "id": "4e84d50c709f03bb1b000077"}, {"name": "AK", "zip": "19010", "created": 1317328062, "time": "16:27:42", "date": "11-09-29", "id": "4e84d4becf436af30900007f"}, {"name": "JM", "zip": "48130", "created": 1317328036, "time": "16:27:16", "date": "11-09-29", "id": "4e84d4a4ec309e941b000057"}, {"name": "AL", "zip": "78300", "created": 1317327936, "time": "16:25:36", "date": "11-09-29", "id": "4e84d4409cd1c1b00900005a"}, {"name": "VP", "zip": "22712", "created": 1317327867, "time": "16:24:27", "date": "11-09-29", "id": "4e84d3fb2ee8d0671700005b"}, {"name": "GK", "zip": "", "created": 1317327843, "time": "16:24:03", "date": "11-09-29", "id": "4e84d3e353b2cf140700004c"}, {"name": "MU", "zip": "95501", "created": 1317327803, "time": "16:23:23", "date": "11-09-29", "id": "4e84d3bbec309e5b1b00005e"}, {"name": "CC", "zip": "21776", "created": 1317327783, "time": "16:23:03", "date": "11-09-29", "id": "4e84d3a7b25636bc0100000e"}, {"name": "AD", "zip": "60012", "created": 1317327734, "time": "16:22:14", "date": "11-09-29", "id": "4e84d3769cd1c1ce0900005f"}, {"name": "KD", "zip": "74136", "created": 1317327648, "time": "16:20:48", "date": "11-09-29", "id": "4e84d320fb7528530c00005b"}, {"name": "GM", "zip": "21122", "created": 1317327376, "time": "16:16:16", "date": "11-09-29", "id": "4e84d2104bd504111d00005d"}, {"name": "MM", "zip": "74114", "created": 1317327355, "time": "16:15:55", "date": "11-09-29", "id": "4e84d1fb53b2cf0907000062"}, {"name": "AM", "zip": "55306", "created": 1317327354, "time": "16:15:54", "date": "11-09-29", "id": "4e84d1fa11fb9cd40f000067"}, {"name": "DE", "zip": "33133", "created": 1317327299, "time": "16:14:59", "date": "11-09-29", "id": "4e84d1c3709f03bb1b000072"}, {"name": "DR", "zip": "02536", "created": 1317327226, "time": "16:13:46", "date": "11-09-29", "id": "4e84d17aec309e681b000057"}, {"name": "JB", "zip": "20152", "created": 1317326977, "time": "16:09:37", "date": "11-09-29", "id": "4e84d0812ee8d0c074000009"}, {"name": "MF", "zip": "07506", "created": 1317326812, "time": "16:06:52", "date": "11-09-29", "id": "4e84cfdc53b2cfb63700000f"}, {"name": "TB", "zip": "33549", "created": 1317326728, "time": "16:05:28", "date": "11-09-29", "id": "4e84cf884bd504ef07000007"}, {"name": "MT", "zip": "80302", "created": 1317326666, "time": "16:04:26", "date": "11-09-29", "id": "4e84cf4ab256362a0b00005e"}, {"name": "CS", "zip": "21228", "created": 1317326251, "time": "15:57:31", "date": "11-09-29", "id": "4e84cdab53b2cf1f07000068"}, {"name": "EA", "zip": "01701", "created": 1317326201, "time": "15:56:41", "date": "11-09-29", "id": "4e84cd792ee8d04b1700005f"}, {"name": "JW", "zip": "29154", "created": 1317326181, "time": "15:56:21", "date": "11-09-29", "id": "4e84cd658d8c375215000056"}, {"name": "NS", "zip": "94582", "created": 1317325889, "time": "15:51:29", "date": "11-09-29", "id": "4e84cc41ec309e5b1b000059"}, {"name": "CS", "zip": "", "created": 1317325447, "time": "15:44:07", "date": "11-09-29", "id": "4e84ca87b25636b70a000052"}, {"name": "KP", "zip": "43615", "created": 1317325447, "time": "15:44:07", "date": "11-09-29", "id": "4e84ca872ee8d0bd74000009"}, {"name": "AC", "zip": "", "created": 1317325400, "time": "15:43:20", "date": "11-09-29", "id": "4e84ca5853b2cf0407000054"}, {"name": "ED", "zip": "14530", "created": 1317325242, "time": "15:40:42", "date": "11-09-29", "id": "4e84c9ba8d8c374215000052"}, {"name": "CM", "zip": "48047", "created": 1317325145, "time": "15:39:05", "date": "11-09-29", "id": "4e84c9599cd1c1bf09000060"}, {"name": "RD", "zip": "53210", "created": 1317325045, "time": "15:37:25", "date": "11-09-29", "id": "4e84c8f54bd5040d1d000051"}, {"name": "DW", "zip": "37415", "created": 1317325006, "time": "15:36:46", "date": "11-09-29", "id": "4e84c8ce8d8c37c67b000002"}, {"name": "DF", "zip": "02906", "created": 1317325003, "time": "15:36:43", "date": "11-09-29", "id": "4e84c8cb9cd1c1a709000062"}, {"name": "MS", "zip": "93309", "created": 1317324997, "time": "15:36:37", "date": "11-09-29", "id": "4e84c8c553b2cf210700003d"}, {"name": "BA", "zip": "20902", "created": 1317324936, "time": "15:35:36", "date": "11-09-29", "id": "4e84c888ec309e951b000057"}, {"name": "GO", "zip": "49048", "created": 1317324686, "time": "15:31:26", "date": "11-09-29", "id": "4e84c78e11fb9cde0f000058"}, {"name": "BR", "zip": "90049", "created": 1317324678, "time": "15:31:18", "date": "11-09-29", "id": "4e84c786709f03d41b000059"}, {"name": "TW", "zip": "35763", "created": 1317324642, "time": "15:30:42", "date": "11-09-29", "id": "4e84c7624bd504081d000050"}, {"name": "DL", "zip": "90046", "created": 1317324603, "time": "15:30:03", "date": "11-09-29", "id": "4e84c73bb25636860a00005d"}, {"name": "JM", "zip": "76106", "created": 1317324501, "time": "15:28:21", "date": "11-09-29", "id": "4e84c6d5709f03b01b00004f"}, {"name": "ad", "zip": "14564", "created": 1317324471, "time": "15:27:51", "date": "11-09-29", "id": "4e84c6b7ec309e6b1b000057"}, {"name": "EB", "zip": "95821", "created": 1317324449, "time": "15:27:29", "date": "11-09-29", "id": "4e84c6a1fb75285f0c000065"}, {"name": "vf", "zip": "21111", "created": 1317324401, "time": "15:26:41", "date": "11-09-29", "id": "4e84c671ec309e1e03000004"}, {"name": "TW", "zip": "95050", "created": 1317324333, "time": "15:25:33", "date": "11-09-29", "id": "4e84c62d4bd504161d000059"}, {"name": "CM", "zip": "11225", "created": 1317324020, "time": "15:20:20", "date": "11-09-29", "id": "4e84c4f411fb9caf5c000009"}, {"name": "KC", "zip": "27573", "created": 1317323689, "time": "15:14:49", "date": "11-09-29", "id": "4e84c3a99cd1c1bb09000047"}, {"name": "KC", "zip": "23831", "created": 1317323407, "time": "15:10:07", "date": "11-09-29", "id": "4e84c28ffb7528580c00004c"}, {"name": "kk", "zip": "30342", "created": 1317323364, "time": "15:09:24", "date": "11-09-29", "id": "4e84c2642ee8d05917000051"}, {"name": "WH", "zip": "01523", "created": 1317323287, "time": "15:08:07", "date": "11-09-29", "id": "4e84c217ec309e671b000046"}, {"name": "JB", "zip": "95064", "created": 1317323238, "time": "15:07:18", "date": "11-09-29", "id": "4e84c1e6cf436aff0900004c"}, {"name": "SV", "zip": "14701", "created": 1317323162, "time": "15:06:02", "date": "11-09-29", "id": "4e84c19a2ee8d05717000064"}, {"name": "TC", "zip": "53032", "created": 1317322913, "time": "15:01:53", "date": "11-09-29", "id": "4e84c0a14bd5041c1d000054"}, {"name": "EW", "zip": "91784", "created": 1317322838, "time": "15:00:38", "date": "11-09-29", "id": "4e84c056ec309ee81b000047"}, {"name": "KB", "zip": "85207", "created": 1317322759, "time": "14:59:19", "date": "11-09-29", "id": "4e84c007709f03b81b00005a"}, {"name": "tc", "zip": "96791", "created": 1317322639, "time": "14:57:19", "date": "11-09-29", "id": "4e84bf8ffb75285b0c000053"}, {"name": "SH", "zip": "75287", "created": 1317322624, "time": "14:57:04", "date": "11-09-29", "id": "4e84bf804bd504181d000045"}, {"name": "SH", "zip": "78731", "created": 1317322570, "time": "14:56:10", "date": "11-09-29", "id": "4e84bf4a2ee8d04917000057"}, {"name": "FH", "zip": "22206", "created": 1317322503, "time": "14:55:03", "date": "11-09-29", "id": "4e84bf07b256362a0b00004a"}, {"name": "rB", "zip": "98125", "created": 1317322376, "time": "14:52:56", "date": "11-09-29", "id": "4e84be884bd504161d000055"}, {"name": "CB", "zip": "48336", "created": 1317322339, "time": "14:52:19", "date": "11-09-29", "id": "4e84be63cf436aed09000044"}, {"name": "RM", "zip": "94118", "created": 1317322337, "time": "14:52:17", "date": "11-09-29", "id": "4e84be618d8c37fc1e00003d"}, {"name": "AV", "zip": "61455", "created": 1317322336, "time": "14:52:16", "date": "11-09-29", "id": "4e84be60ec309e7e1b00004e"}, {"name": "SG", "zip": "80302", "created": 1317322295, "time": "14:51:35", "date": "11-09-29", "id": "4e84be374bd504111d00004b"}, {"name": "AG", "zip": "60610", "created": 1317322099, "time": "14:48:19", "date": "11-09-29", "id": "4e84bd73709f03df1c000054"}, {"name": "DH", "zip": "60007", "created": 1317322081, "time": "14:48:01", "date": "11-09-29", "id": "4e84bd618d8c374315000034"}, {"name": "NH", "zip": "80031", "created": 1317321857, "time": "14:44:17", "date": "11-09-29", "id": "4e84bc814bd504281d000046"}, {"name": "LH", "zip": "14605", "created": 1317321827, "time": "14:43:47", "date": "11-09-29", "id": "4e84bc63cf436a020a00005e"}, {"name": "BK", "zip": "32653", "created": 1317321621, "time": "14:40:21", "date": "11-09-29", "id": "4e84bb95709f039f1b00004d"}, {"name": "DB", "zip": "30327", "created": 1317321617, "time": "14:40:17", "date": "11-09-29", "id": "4e84bb91ec309e951b00004f"}, {"name": "MD", "zip": "55407", "created": 1317321595, "time": "14:39:55", "date": "11-09-29", "id": "4e84bb7b9cd1c1b509000055"}, {"name": "JB", "zip": "80026", "created": 1317321543, "time": "14:39:03", "date": "11-09-29", "id": "4e84bb4753b2cf1707000051"}, {"name": "BP", "zip": "75202", "created": 1317321354, "time": "14:35:54", "date": "11-09-29", "id": "4e84ba8a2ee8d03717000040"}, {"name": "AN", "zip": "41075", "created": 1317321332, "time": "14:35:32", "date": "11-09-29", "id": "4e84ba74cf436afa09000040"}, {"name": "TW", "zip": "44273", "created": 1317321251, "time": "14:34:11", "date": "11-09-29", "id": "4e84ba23ec309e5e1f000045"}, {"name": "GM", "zip": "85282", "created": 1317321080, "time": "14:31:20", "date": "11-09-29", "id": "4e84b9789cd1c1b509000054"}, {"name": "JI", "zip": "", "created": 1317321012, "time": "14:30:12", "date": "11-09-29", "id": "4e84b93453b2cf0507000045"}, {"name": "JB", "zip": "21113", "created": 1317320955, "time": "14:29:15", "date": "11-09-29", "id": "4e84b8fbcf436aef09000035"}, {"name": "ZS", "zip": "41653", "created": 1317320886, "time": "14:28:06", "date": "11-09-29", "id": "4e84b8b6709f03bd1b00004a"}, {"name": "SD", "zip": "", "created": 1317320720, "time": "14:25:20", "date": "11-09-29", "id": "4e84b810fb75285e0c000044"}, {"name": "MC", "zip": "43081", "created": 1317320269, "time": "14:17:49", "date": "11-09-29", "id": "4e84b64dfb7528510c00004c"}, {"name": "PB", "zip": "31632", "created": 1317320216, "time": "14:16:56", "date": "11-09-29", "id": "4e84b61811fb9cea0f00003f"}, {"name": "SM", "zip": "23452", "created": 1317319985, "time": "14:13:05", "date": "11-09-29", "id": "4e84b5314bd504141d000051"}, {"name": "SD", "zip": "10012", "created": 1317319924, "time": "14:12:04", "date": "11-09-29", "id": "4e84b4f48d8c37fc1e000038"}, {"name": "KJ", "zip": "60056", "created": 1317319803, "time": "14:10:03", "date": "11-09-29", "id": "4e84b47bcf436a0a0a000039"}, {"name": "JC", "zip": "14072", "created": 1317319776, "time": "14:09:36", "date": "11-09-29", "id": "4e84b4602ee8d0421700004f"}, {"name": "CA", "zip": "11590", "created": 1317319712, "time": "14:08:32", "date": "11-09-29", "id": "4e84b420709f039e1b00003b"}, {"name": "JG", "zip": "14607", "created": 1317319661, "time": "14:07:41", "date": "11-09-29", "id": "4e84b3ed4bd504141d000050"}, {"name": "ES", "zip": "87122", "created": 1317319513, "time": "14:05:13", "date": "11-09-29", "id": "4e84b359cf436a050a000037"}, {"name": "RO", "zip": "66614", "created": 1317319193, "time": "13:59:53", "date": "11-09-29", "id": "4e84b21953b2cf1607000046"}, {"name": "CH", "zip": "72019", "created": 1317319048, "time": "13:57:28", "date": "11-09-29", "id": "4e84b1882ee8d04b17000049"}, {"name": "KC", "zip": "78758", "created": 1317318958, "time": "13:55:58", "date": "11-09-29", "id": "4e84b12e2ee8d0341700004a"}, {"name": "KK", "zip": "73072", "created": 1317318696, "time": "13:51:36", "date": "11-09-29", "id": "4e84b028fb75284f0c00004e"}, {"name": "NC", "zip": "85201", "created": 1317318451, "time": "13:47:31", "date": "11-09-29", "id": "4e84af33cf436af20900004c"}, {"name": "TL", "zip": "85013", "created": 1317318362, "time": "13:46:02", "date": "11-09-29", "id": "4e84aeda53b2cf150700003d"}, {"name": "DH", "zip": "08753", "created": 1317318223, "time": "13:43:43", "date": "11-09-29", "id": "4e84ae4f53b2cf1a07000050"}, {"name": "ML", "zip": "33701", "created": 1317318122, "time": "13:42:02", "date": "11-09-29", "id": "4e84adea2ee8d05a17000040"}, {"name": "JE", "zip": "60647", "created": 1317318031, "time": "13:40:31", "date": "11-09-29", "id": "4e84ad8fec309ee81b00003b"}, {"name": "EY", "zip": "20007", "created": 1317317687, "time": "13:34:47", "date": "11-09-29", "id": "4e84ac372ee8d0071a00003e"}, {"name": "DS", "zip": "32503", "created": 1317317679, "time": "13:34:39", "date": "11-09-29", "id": "4e84ac2f709f03ce1b00004b"}, {"name": "vg", "zip": "89134", "created": 1317317675, "time": "13:34:35", "date": "11-09-29", "id": "4e84ac2b11fb9ce40f00004a"}, {"name": "RS", "zip": "90504", "created": 1317317639, "time": "13:33:59", "date": "11-09-29", "id": "4e84ac0711fb9cd60f000049"}, {"name": "KS", "zip": "11553", "created": 1317317546, "time": "13:32:26", "date": "11-09-29", "id": "4e84abaaec309e161c00003f"}, {"name": "VN", "zip": "55408", "created": 1317317426, "time": "13:30:26", "date": "11-09-29", "id": "4e84ab32b25636b70a000042"}, {"name": "DW", "zip": "98118", "created": 1317317384, "time": "13:29:44", "date": "11-09-29", "id": "4e84ab0811fb9cd80f00003d"}, {"name": "JD", "zip": "94133", "created": 1317317143, "time": "13:25:43", "date": "11-09-29", "id": "4e84aa172ee8d03717000039"}, {"name": "AB", "zip": "21217", "created": 1317316958, "time": "13:22:38", "date": "11-09-29", "id": "4e84a95eb25636a50a000038"}, {"name": "JU", "zip": "35801", "created": 1317316862, "time": "13:21:02", "date": "11-09-29", "id": "4e84a8fe11fb9cd40f000046"}, {"name": "AC", "zip": "21209", "created": 1317316833, "time": "13:20:33", "date": "11-09-29", "id": "4e84a8e19cd1c1a609000047"}, {"name": "JG", "zip": "10567", "created": 1317316813, "time": "13:20:13", "date": "11-09-29", "id": "4e84a8cd11fb9cec0f00004e"}, {"name": "CL", "zip": "46545", "created": 1317316768, "time": "13:19:28", "date": "11-09-29", "id": "4e84a8a011fb9cdd0f000047"}, {"name": "AW", "zip": "17557", "created": 1317316698, "time": "13:18:18", "date": "11-09-29", "id": "4e84a85a2ee8d04017000047"}, {"name": "JV", "zip": "86001", "created": 1317316526, "time": "13:15:26", "date": "11-09-29", "id": "4e84a7ae11fb9ce60f000036"}, {"name": "JD", "zip": "20785", "created": 1317316275, "time": "13:11:15", "date": "11-09-29", "id": "4e84a6b311fb9cd30f00004f"}, {"name": "CT", "zip": "46176", "created": 1317315998, "time": "13:06:38", "date": "11-09-29", "id": "4e84a59e9cd1c1ae0900004a"}, {"name": "CM", "zip": "81301", "created": 1317315812, "time": "13:03:32", "date": "11-09-29", "id": "4e84a4e49cd1c1be09000042"}, {"name": "RG", "zip": "43214", "created": 1317315760, "time": "13:02:40", "date": "11-09-29", "id": "4e84a4b0709f03c61b000030"}, {"name": "VS", "zip": "18411", "created": 1317315732, "time": "13:02:12", "date": "11-09-29", "id": "4e84a494fb7528520c00004a"}, {"name": "JW", "zip": "18519", "created": 1317315667, "time": "13:01:07", "date": "11-09-29", "id": "4e84a453709f03a11b00002b"}, {"name": "ZS", "zip": "71037", "created": 1317315513, "time": "12:58:33", "date": "11-09-29", "id": "4e84a3b911fb9ce30f000048"}, {"name": "AB", "zip": "93003", "created": 1317315504, "time": "12:58:24", "date": "11-09-29", "id": "4e84a3b04bd504051d00002f"}, {"name": "ES", "zip": "", "created": 1317315336, "time": "12:55:36", "date": "11-09-29", "id": "4e84a308ec309e5a1b00003f"}, {"name": "SH", "zip": "20817", "created": 1317315289, "time": "12:54:49", "date": "11-09-29", "id": "4e84a2d99cd1c1b00900003d"}, {"name": "Jf", "zip": "08648", "created": 1317315277, "time": "12:54:37", "date": "11-09-29", "id": "4e84a2cdfb75284d0c000035"}, {"name": "TC", "zip": "11234", "created": 1317315163, "time": "12:52:43", "date": "11-09-29", "id": "4e84a25b4bd504171d000039"}, {"name": "jt", "zip": "24301", "created": 1317315037, "time": "12:50:37", "date": "11-09-29", "id": "4e84a1dd2ee8d0021a000046"}, {"name": "JK", "zip": "27606", "created": 1317314982, "time": "12:49:42", "date": "11-09-29", "id": "4e84a1a6709f039d1b000039"}, {"name": "MF", "zip": "28031", "created": 1317314960, "time": "12:49:20", "date": "11-09-29", "id": "4e84a190709f03ce1b000044"}, {"name": "JW", "zip": "84105", "created": 1317314924, "time": "12:48:44", "date": "11-09-29", "id": "4e84a16c9cd1c1b509000048"}, {"name": "TO", "zip": "56701", "created": 1317314923, "time": "12:48:43", "date": "11-09-29", "id": "4e84a16bec309e7d1b00003d"}, {"name": "JM", "zip": "77007", "created": 1317314839, "time": "12:47:19", "date": "11-09-29", "id": "4e84a1174bd504151d000024"}, {"name": "JS", "zip": "44306", "created": 1317314805, "time": "12:46:45", "date": "11-09-29", "id": "4e84a0f5b256369d0a00003d"}, {"name": "MR", "zip": "90815", "created": 1317314772, "time": "12:46:12", "date": "11-09-29", "id": "4e84a0d4709f03bd1b00003d"}, {"name": "LG", "zip": "95136", "created": 1317314722, "time": "12:45:22", "date": "11-09-29", "id": "4e84a0a24bd504021d000036"}, {"name": "CA", "zip": "27606", "created": 1317314468, "time": "12:41:08", "date": "11-09-29", "id": "4e849fa42ee8d04917000047"}, {"name": "DF", "zip": "20904", "created": 1317314460, "time": "12:41:00", "date": "11-09-29", "id": "4e849f9ccf436afc09000038"}, {"name": "MS", "zip": "08812", "created": 1317314164, "time": "12:36:04", "date": "11-09-29", "id": "4e849e7453b2cf0507000034"}, {"name": "ES", "zip": "84044", "created": 1317314149, "time": "12:35:49", "date": "11-09-29", "id": "4e849e65709f03a01b000029"}, {"name": "SS", "zip": "49333", "created": 1317314148, "time": "12:35:48", "date": "11-09-29", "id": "4e849e64cf436a010a00003b"}, {"name": "wt", "zip": "33414", "created": 1317314134, "time": "12:35:34", "date": "11-09-29", "id": "4e849e562ee8d04317000034"}, {"name": "JB", "zip": "02467", "created": 1317314125, "time": "12:35:25", "date": "11-09-29", "id": "4e849e4d4bd504141d00003c"}, {"name": "EB", "zip": "79934", "created": 1317314084, "time": "12:34:44", "date": "11-09-29", "id": "4e849e24fb75284e0c000032"}, {"name": "JB", "zip": "", "created": 1317313777, "time": "12:29:37", "date": "11-09-29", "id": "4e849cf1fb7528590c00003c"}, {"name": "sa", "zip": "77479", "created": 1317313750, "time": "12:29:10", "date": "11-09-29", "id": "4e849cd6cf436af409000044"}, {"name": "DE", "zip": "21211", "created": 1317313709, "time": "12:28:29", "date": "11-09-29", "id": "4e849cad8d8c37441500002e"}, {"name": "DP", "zip": "14108", "created": 1317313487, "time": "12:24:47", "date": "11-09-29", "id": "4e849bcfcf436af30900004a"}, {"name": "DA", "zip": "21122", "created": 1317313345, "time": "12:22:25", "date": "11-09-29", "id": "4e849b41ec309e7e1b000039"}, {"name": "RG", "zip": "14620", "created": 1317313334, "time": "12:22:14", "date": "11-09-29", "id": "4e849b36b25636a50a000031"}, {"name": "MC", "zip": "78704", "created": 1317313279, "time": "12:21:19", "date": "11-09-29", "id": "4e849aff2ee8d06617000041"}, {"name": "LC", "zip": "82604", "created": 1317313179, "time": "12:19:39", "date": "11-09-29", "id": "4e849a9b11fb9c8e10000038"}, {"name": "JS", "zip": "", "created": 1317313049, "time": "12:17:29", "date": "11-09-29", "id": "4e849a192ee8d05b17000039"}, {"name": "RL", "zip": "32724", "created": 1317312935, "time": "12:15:35", "date": "11-09-29", "id": "4e8499a7709f039d1b000038"}, {"name": "ER", "zip": "97355", "created": 1317312894, "time": "12:14:54", "date": "11-09-29", "id": "4e84997e53b2cf2b0700003b"}, {"name": "SW", "zip": "19341", "created": 1317312552, "time": "12:09:12", "date": "11-09-29", "id": "4e849828709f039f1b000033"}, {"name": "JB", "zip": "93545", "created": 1317312532, "time": "12:08:52", "date": "11-09-29", "id": "4e849814709f039f1b000032"}, {"name": "SG", "zip": "92109", "created": 1317312388, "time": "12:06:28", "date": "11-09-29", "id": "4e849784cf436af909000036"}, {"name": "CG", "zip": "85118", "created": 1317312008, "time": "12:00:08", "date": "11-09-29", "id": "4e849608cf436aed0900002c"}, {"name": "LC", "zip": "75035", "created": 1317311920, "time": "11:58:40", "date": "11-09-29", "id": "4e8495b0709f03b01b000034"}, {"name": "BR", "zip": "49221", "created": 1317311655, "time": "11:54:15", "date": "11-09-29", "id": "4e8494a79cd1c1cf09000032"}, {"name": "JR", "zip": "34471", "created": 1317311567, "time": "11:52:47", "date": "11-09-29", "id": "4e84944f8d8c374115000033"}, {"name": "JS", "zip": "", "created": 1317311499, "time": "11:51:39", "date": "11-09-29", "id": "4e84940b53b2cf1607000037"}, {"name": "QB", "zip": "32224", "created": 1317311347, "time": "11:49:07", "date": "11-09-29", "id": "4e849373709f03d41b00003a"}, {"name": "JF", "zip": "06854", "created": 1317311207, "time": "11:46:47", "date": "11-09-29", "id": "4e8492e7b25636910a00003a"}, {"name": "BA", "zip": "32927", "created": 1317311183, "time": "11:46:23", "date": "11-09-29", "id": "4e8492cf709f03df1c00003d"}, {"name": "SM", "zip": "19103", "created": 1317311009, "time": "11:43:29", "date": "11-09-29", "id": "4e84922111fb9cdf0f00003a"}, {"name": "AW", "zip": "30134", "created": 1317310990, "time": "11:43:10", "date": "11-09-29", "id": "4e84920e2ee8d04a17000028"}, {"name": "mc", "zip": "30101", "created": 1317310955, "time": "11:42:35", "date": "11-09-29", "id": "4e8491ebec309e7b1b000026"}, {"name": "JS", "zip": "77536", "created": 1317310928, "time": "11:42:08", "date": "11-09-29", "id": "4e8491d0b256369a0a000030"}, {"name": "JB", "zip": "40207", "created": 1317310868, "time": "11:41:08", "date": "11-09-29", "id": "4e849194ec309e5e1b000032"}, {"name": "LJ", "zip": "78612", "created": 1317310840, "time": "11:40:40", "date": "11-09-29", "id": "4e849178fb7528530c000036"}, {"name": "DG", "zip": "78757", "created": 1317310833, "time": "11:40:33", "date": "11-09-29", "id": "4e8491718d8c375f15000033"}, {"name": "ca", "zip": "57702", "created": 1317310682, "time": "11:38:02", "date": "11-09-29", "id": "4e8490dacf436a000a000030"}, {"name": "RL", "zip": "11571", "created": 1317310637, "time": "11:37:17", "date": "11-09-29", "id": "4e8490ad9cd1c1ba09000038"}, {"name": "AT", "zip": "47302", "created": 1317310405, "time": "11:33:25", "date": "11-09-29", "id": "4e848fc511fb9cd80f000030"}, {"name": "BV", "zip": "92808", "created": 1317310345, "time": "11:32:25", "date": "11-09-29", "id": "4e848f894bd5040d1d000032"}, {"name": "TM", "zip": "79414", "created": 1317309983, "time": "11:26:23", "date": "11-09-29", "id": "4e848e1f4bd504141d000032"}, {"name": "LW", "zip": "50111", "created": 1317309934, "time": "11:25:34", "date": "11-09-29", "id": "4e848deefb75285b0c000034"}, {"name": "BS", "zip": "", "created": 1317309892, "time": "11:24:52", "date": "11-09-29", "id": "4e848dc453b2cfd71900002b"}, {"name": "ZK", "zip": "55104", "created": 1317309886, "time": "11:24:46", "date": "11-09-29", "id": "4e848dbe53b2cf1307000032"}, {"name": "FP", "zip": "20151-1325", "created": 1317309711, "time": "11:21:51", "date": "11-09-29", "id": "4e848d0f709f03b71b00003c"}, {"name": "MS", "zip": "60707", "created": 1317309696, "time": "11:21:36", "date": "11-09-29", "id": "4e848d002ee8d0451700003d"}, {"name": "JM", "zip": "60137", "created": 1317309693, "time": "11:21:33", "date": "11-09-29", "id": "4e848cfdcf436aea0900002b"}, {"name": "om", "zip": "32750", "created": 1317309527, "time": "11:18:47", "date": "11-09-29", "id": "4e848c578d8c374d1500002e"}, {"name": "JR", "zip": "49008", "created": 1317309518, "time": "11:18:38", "date": "11-09-29", "id": "4e848c4e11fb9ce60f000026"}, {"name": "CH", "zip": "80301", "created": 1317309435, "time": "11:17:15", "date": "11-09-29", "id": "4e848bfb9cd1c1a809000026"}, {"name": "FC", "zip": "02743", "created": 1317309391, "time": "11:16:31", "date": "11-09-29", "id": "4e848bcfec309e791b00003c"}, {"name": "KB", "zip": "05829", "created": 1317309064, "time": "11:11:04", "date": "11-09-29", "id": "4e848a8853b2cf160700002e"}, {"name": "db", "zip": "60490", "created": 1317308634, "time": "11:03:54", "date": "11-09-29", "id": "4e8488da4bd504081d00002b"}, {"name": "AR", "zip": "71913", "created": 1317308597, "time": "11:03:17", "date": "11-09-29", "id": "4e8488b511fb9cd30f000045"}, {"name": "BV", "zip": "", "created": 1317308419, "time": "11:00:19", "date": "11-09-29", "id": "4e848803709f03ad1b000022"}, {"name": "ER", "zip": "32809-3520", "created": 1317308251, "time": "10:57:31", "date": "11-09-29", "id": "4e84875b9cd1c1a809000023"}, {"name": "EZ", "zip": "19802", "created": 1317308192, "time": "10:56:32", "date": "11-09-29", "id": "4e8487202ee8d04117000032"}, {"name": "kb", "zip": "78123", "created": 1317308118, "time": "10:55:18", "date": "11-09-29", "id": "4e8486d69cd1c1c00900002e"}, {"name": "CN", "zip": "10010", "created": 1317307970, "time": "10:52:50", "date": "11-09-29", "id": "4e8486422ee8d0491700002e"}, {"name": "NN", "zip": "78702", "created": 1317307716, "time": "10:48:36", "date": "11-09-29", "id": "4e848544fb75285f0c000033"}, {"name": "CM", "zip": "", "created": 1317307540, "time": "10:45:40", "date": "11-09-29", "id": "4e8484948d8c37571500001c"}, {"name": "CL", "zip": "30096", "created": 1317307531, "time": "10:45:31", "date": "11-09-29", "id": "4e84848b53b2cf2507000025"}, {"name": "GS", "zip": "37919", "created": 1317307522, "time": "10:45:22", "date": "11-09-29", "id": "4e848482fb7528580c000029"}, {"name": "CR", "zip": "76227", "created": 1317307218, "time": "10:40:18", "date": "11-09-29", "id": "4e848352b256369b0a00002f"}, {"name": "GP", "zip": "21502", "created": 1317307099, "time": "10:38:19", "date": "11-09-29", "id": "4e8482db8d8c37571500001a"}, {"name": "Am", "zip": "48038", "created": 1317307094, "time": "10:38:14", "date": "11-09-29", "id": "4e8482d6ec309e5a1b00002c"}, {"name": "MT", "zip": "84720", "created": 1317307068, "time": "10:37:48", "date": "11-09-29", "id": "4e8482bc4bd504031d000034"}, {"name": "KG", "zip": "17019", "created": 1317307059, "time": "10:37:39", "date": "11-09-29", "id": "4e8482b3fb7528540c00001c"}, {"name": "RW", "zip": "64012", "created": 1317307022, "time": "10:37:02", "date": "11-09-29", "id": "4e84828eb256362f1f000033"}, {"name": "PC", "zip": "", "created": 1317307014, "time": "10:36:54", "date": "11-09-29", "id": "4e8482868d8c375315000030"}, {"name": "JB", "zip": "29316", "created": 1317306782, "time": "10:33:02", "date": "11-09-29", "id": "4e84819eec309e5c1b00002a"}, {"name": "SG", "zip": "72704", "created": 1317306734, "time": "10:32:14", "date": "11-09-29", "id": "4e84816eb25636980a000030"}, {"name": "TV", "zip": "12047", "created": 1317305922, "time": "10:18:42", "date": "11-09-29", "id": "4e847e428d8c37fc1e000023"}, {"name": "CJ", "zip": "27249", "created": 1317305773, "time": "10:16:13", "date": "11-09-29", "id": "4e847dad9cd1c1ba0900002d"}, {"name": "LU", "zip": "60008", "created": 1317305708, "time": "10:15:08", "date": "11-09-29", "id": "4e847d6c709f03b81b00002a"}, {"name": "GC", "zip": "15001", "created": 1317305688, "time": "10:14:48", "date": "11-09-29", "id": "4e847d5811fb9ce40f00002f"}, {"name": "JA", "zip": "", "created": 1317305519, "time": "10:11:59", "date": "11-09-29", "id": "4e847caf9cd1c1b709000021"}, {"name": "VV", "zip": "", "created": 1317305341, "time": "10:09:01", "date": "11-09-29", "id": "4e847bfd4bd504161d000035"}, {"name": "BB", "zip": "91344", "created": 1317305177, "time": "10:06:17", "date": "11-09-29", "id": "4e847b5911fb9cd40f000029"}, {"name": "MT", "zip": "27519", "created": 1317305170, "time": "10:06:10", "date": "11-09-29", "id": "4e847b528d8c374d15000024"}, {"name": "MD", "zip": "76209", "created": 1317304983, "time": "10:03:03", "date": "11-09-29", "id": "4e847a9711fb9cdf0f000034"}, {"name": "RM", "zip": "16801", "created": 1317304777, "time": "09:59:37", "date": "11-09-29", "id": "4e8479c9b256369f0a00001e"}, {"name": "MJ", "zip": "75494", "created": 1317304488, "time": "09:54:48", "date": "11-09-29", "id": "4e8478a8ec309e7a1b000028"}, {"name": "JP", "zip": "06480", "created": 1317304403, "time": "09:53:23", "date": "11-09-29", "id": "4e847853fb7528510c000020"}, {"name": "DD", "zip": "66606", "created": 1317304365, "time": "09:52:45", "date": "11-09-29", "id": "4e84782dec309e9c1b000028"}, {"name": "AS", "zip": "77546", "created": 1317304256, "time": "09:50:56", "date": "11-09-29", "id": "4e8477c09cd1c1ac09000033"}, {"name": "TB", "zip": "08854", "created": 1317304084, "time": "09:48:04", "date": "11-09-29", "id": "4e8477148d8c37411500002d"}, {"name": "LY", "zip": "21210", "created": 1317304067, "time": "09:47:47", "date": "11-09-29", "id": "4e84770311fb9cd90f00002b"}, {"name": "RG", "zip": "34691", "created": 1317303810, "time": "09:43:30", "date": "11-09-29", "id": "4e847602ec309e691b00001f"}, {"name": "RE", "zip": "10305", "created": 1317303592, "time": "09:39:52", "date": "11-09-29", "id": "4e847528fb7528550c00002c"}, {"name": "RC", "zip": "20910", "created": 1317303559, "time": "09:39:19", "date": "11-09-29", "id": "4e847507709f03051c00001f"}, {"name": "KP", "zip": "95076", "created": 1317303182, "time": "09:33:02", "date": "11-09-29", "id": "4e84738eec309e5b1b000024"}, {"name": "PG", "zip": "64085", "created": 1317303119, "time": "09:31:59", "date": "11-09-29", "id": "4e84734f9cd1c1b90900002b"}, {"name": "cp", "zip": "58278", "created": 1317303093, "time": "09:31:33", "date": "11-09-29", "id": "4e84733553b2cf070700002e"}, {"name": "CR", "zip": "33442", "created": 1317302994, "time": "09:29:54", "date": "11-09-29", "id": "4e8472d29cd1c1ab0900001a"}, {"name": "RM", "zip": "92284", "created": 1317302893, "time": "09:28:13", "date": "11-09-29", "id": "4e84726dec309e7b1b000019"}, {"name": "FG", "zip": "11218-4104", "created": 1317302851, "time": "09:27:31", "date": "11-09-29", "id": "4e8472439cd1c1ae09000026"}, {"name": "RB", "zip": "48104", "created": 1317302804, "time": "09:26:44", "date": "11-09-29", "id": "4e84721453b2cf2b0700002d"}, {"name": "LP", "zip": "32308", "created": 1317301894, "time": "09:11:34", "date": "11-09-29", "id": "4e846e862ee8d04c17000018"}, {"name": "JD", "zip": "23430", "created": 1317301787, "time": "09:09:47", "date": "11-09-29", "id": "4e846e1b2ee8d0411700002c"}, {"name": "gg", "zip": "03784", "created": 1317300906, "time": "08:55:06", "date": "11-09-29", "id": "4e846aaa53b2cf080700002c"}, {"name": "SO", "zip": "", "created": 1317300653, "time": "08:50:53", "date": "11-09-29", "id": "4e8469ad709f03bb1b000027"}, {"name": "DS", "zip": "98198", "created": 1317300230, "time": "08:43:50", "date": "11-09-29", "id": "4e84680653b2cf210700001a"}, {"name": "CB", "zip": "33428", "created": 1317299886, "time": "08:38:06", "date": "11-09-29", "id": "4e8466aeb25636a40a000014"}, {"name": "PB", "zip": "92264", "created": 1317298902, "time": "08:21:42", "date": "11-09-29", "id": "4e8462d68d8c37581500002b"}, {"name": "EB", "zip": "", "created": 1317298749, "time": "08:19:09", "date": "11-09-29", "id": "4e84623d2ee8d03617000018"}, {"name": "SK", "zip": "46534", "created": 1317298347, "time": "08:12:27", "date": "11-09-29", "id": "4e8460ab9cd1c1ce09000028"}, {"name": "KB", "zip": "78758-6202", "created": 1317298333, "time": "08:12:13", "date": "11-09-29", "id": "4e84609dec309e6a1b000025"}, {"name": "NB", "zip": "89148", "created": 1317296352, "time": "07:39:12", "date": "11-09-29", "id": "4e8458e011fb9ce30f00001e"}, {"name": "ST", "zip": "27615", "created": 1317296208, "time": "07:36:48", "date": "11-09-29", "id": "4e845850709f039c1b00001d"}, {"name": "GB", "zip": "05091", "created": 1317295462, "time": "07:24:22", "date": "11-09-29", "id": "4e8455662ee8d03f1700001f"}, {"name": "DJ", "zip": "27605", "created": 1317295448, "time": "07:24:08", "date": "11-09-29", "id": "4e845558fb75286d0c000021"}, {"name": "MD", "zip": "19702", "created": 1317294970, "time": "07:16:10", "date": "11-09-29", "id": "4e84537a53b2cfd719000018"}, {"name": "JS", "zip": "60143", "created": 1317294861, "time": "07:14:21", "date": "11-09-29", "id": "4e84530db25636a60a000023"}, {"name": "RF", "zip": "79720", "created": 1317294687, "time": "07:11:27", "date": "11-09-29", "id": "4e84525fcf436a0a0a000013"}, {"name": "FH", "zip": "12095", "created": 1317294674, "time": "07:11:14", "date": "11-09-29", "id": "4e8452524bd5041c1d000023"}, {"name": "JS", "zip": "30601", "created": 1317294525, "time": "07:08:45", "date": "11-09-29", "id": "4e8451bd9cd1c1bb0900001c"}, {"name": "CD", "zip": "37801", "created": 1317294523, "time": "07:08:43", "date": "11-09-29", "id": "4e8451bbec309e7d1b000016"}, {"name": "CJ", "zip": "", "created": 1317294083, "time": "07:01:23", "date": "11-09-29", "id": "4e8450038d8c374c1500001c"}, {"name": "ES", "zip": "", "created": 1317293838, "time": "06:57:18", "date": "11-09-29", "id": "4e844f0e4bd504111d00001a"}, {"name": "RM", "zip": "48047", "created": 1317293635, "time": "06:53:55", "date": "11-09-29", "id": "4e844e438d8c375c1500001e"}, {"name": "JS", "zip": "03087", "created": 1317292690, "time": "06:38:10", "date": "11-09-29", "id": "4e844a92709f039c1b00001b"}, {"name": "AB", "zip": "44709", "created": 1317292495, "time": "06:34:55", "date": "11-09-29", "id": "4e8449cfcf436a0a0a000012"}, {"name": "KH", "zip": "91342", "created": 1317291145, "time": "06:12:25", "date": "11-09-29", "id": "4e84448911fb9c8d1000001d"}, {"name": "KW", "zip": "32301", "created": 1317290997, "time": "06:09:57", "date": "11-09-29", "id": "4e8443f5cf436a521f000010"}, {"name": "RE", "zip": "21224", "created": 1317290823, "time": "06:07:03", "date": "11-09-29", "id": "4e844347b25636a40a000010"}, {"name": "JK", "zip": "77064", "created": 1317289562, "time": "05:46:02", "date": "11-09-29", "id": "4e843e5afb75284e0c00001d"}, {"name": "MR", "zip": "15690", "created": 1317288425, "time": "05:27:05", "date": "11-09-29", "id": "4e8439e9ec309e941b000011"}, {"name": "JR", "zip": "61820", "created": 1317288236, "time": "05:23:56", "date": "11-09-29", "id": "4e84392cec309e7a1b000013"}, {"name": "AM", "zip": "92867", "created": 1317286528, "time": "04:55:28", "date": "11-09-29", "id": "4e843280cf436aef09000015"}, {"name": "LY", "zip": "94087", "created": 1317286328, "time": "04:52:08", "date": "11-09-29", "id": "4e8431b82ee8d04a17000014"}, {"name": "AR", "zip": "44054", "created": 1317286038, "time": "04:47:18", "date": "11-09-29", "id": "4e8430968d8c375315000018"}, {"name": "AH", "zip": "75110", "created": 1317285995, "time": "04:46:35", "date": "11-09-29", "id": "4e84306b4bd504131d000015"}, {"name": "NY", "zip": "27106", "created": 1317285991, "time": "04:46:31", "date": "11-09-29", "id": "4e843067b25636ef1600001d"}, {"name": "GM", "zip": "91786", "created": 1317285553, "time": "04:39:13", "date": "11-09-29", "id": "4e842eb18d8c375115000010"}, {"name": "BS", "zip": "76049-5596", "created": 1317284726, "time": "04:25:26", "date": "11-09-29", "id": "4e842b764bd5042027000010"}, {"name": "TD", "zip": "80516", "created": 1317284370, "time": "04:19:30", "date": "11-09-29", "id": "4e842a1253b2cf1907000019"}, {"name": "jt", "zip": "", "created": 1317284181, "time": "04:16:21", "date": "11-09-29", "id": "4e84295553b2cf130700001a"}, {"name": "KB", "zip": "10026", "created": 1317283968, "time": "04:12:48", "date": "11-09-29", "id": "4e8428802ee8d0491700001a"}, {"name": "MM", "zip": "93551", "created": 1317283745, "time": "04:09:05", "date": "11-09-29", "id": "4e8427a18d8c37581500001f"}, {"name": "HM", "zip": "94112", "created": 1317283285, "time": "04:01:25", "date": "11-09-29", "id": "4e8425d5709f03b91b000019"}, {"name": "KT", "zip": "98541", "created": 1317283163, "time": "03:59:23", "date": "11-09-29", "id": "4e84255b9cd1c1bb09000017"}, {"name": "LA", "zip": "54603", "created": 1317283014, "time": "03:56:54", "date": "11-09-29", "id": "4e8424c611fb9cd30f000022"}, {"name": "JW", "zip": "32826", "created": 1317282830, "time": "03:53:50", "date": "11-09-29", "id": "4e84240eec309e9c1b000018"}, {"name": "AH", "zip": "32707", "created": 1317282436, "time": "03:47:16", "date": "11-09-29", "id": "4e842284b256369c0a000010"}, {"name": "SB", "zip": "86403", "created": 1317281829, "time": "03:37:09", "date": "11-09-29", "id": "4e8420254bd5040e1d00001a"}, {"name": "ao", "zip": "94109", "created": 1317281553, "time": "03:32:33", "date": "11-09-29", "id": "4e841f11cf436a020a000021"}, {"name": "JH", "zip": "94018", "created": 1317281410, "time": "03:30:10", "date": "11-09-29", "id": "4e841e82ec309e7c1b000013"}, {"name": "DB", "zip": "53711", "created": 1317281368, "time": "03:29:28", "date": "11-09-29", "id": "4e841e588d8c374b1500000e"}, {"name": "JW", "zip": "80906", "created": 1317280865, "time": "03:21:05", "date": "11-09-29", "id": "4e841c61fb75285d0c000016"}, {"name": "SJ", "zip": "62704", "created": 1317280806, "time": "03:20:06", "date": "11-09-29", "id": "4e841c26cf436af30900002b"}, {"name": "TH", "zip": "98225", "created": 1317280789, "time": "03:19:49", "date": "11-09-29", "id": "4e841c159cd1c1b409000016"}, {"name": "NI", "zip": "21012", "created": 1317280708, "time": "03:18:28", "date": "11-09-29", "id": "4e841bc4ec309e5e1f00001d"}, {"name": "EA", "zip": "27705", "created": 1317280644, "time": "03:17:24", "date": "11-09-29", "id": "4e841b842ee8d03917000013"}, {"name": "RJ", "zip": "01604", "created": 1317279699, "time": "03:01:39", "date": "11-09-29", "id": "4e8417d311fb9ce90f00001c"}, {"name": "TD", "zip": "18949", "created": 1317279545, "time": "02:59:05", "date": "11-09-29", "id": "4e8417392ee8d03717000016"}, {"name": "SW", "zip": "20007", "created": 1317279279, "time": "02:54:39", "date": "11-09-29", "id": "4e84162f53b2cf200700001b"}, {"name": "MW", "zip": "63134", "created": 1317278889, "time": "02:48:09", "date": "11-09-29", "id": "4e8414a9b25636910a00001a"}, {"name": "sm", "zip": "30316", "created": 1317278722, "time": "02:45:22", "date": "11-09-29", "id": "4e84140253b2cf0a0700001f"}, {"name": "NV", "zip": "48104", "created": 1317278647, "time": "02:44:07", "date": "11-09-29", "id": "4e8413b7fb7528650c000017"}, {"name": "JA", "zip": "98801", "created": 1317278308, "time": "02:38:28", "date": "11-09-29", "id": "4e8412644bd504131d000014"}, {"name": "CD", "zip": "39440", "created": 1317278009, "time": "02:33:29", "date": "11-09-29", "id": "4e84113953b2cf1c07000016"}, {"name": "CW", "zip": "19013-2715", "created": 1317277884, "time": "02:31:24", "date": "11-09-29", "id": "4e8410bc709f03d41b000011"}, {"name": "KW", "zip": "19103", "created": 1317277614, "time": "02:26:54", "date": "11-09-29", "id": "4e840fae2ee8d03717000015"}, {"name": "AB", "zip": "53913", "created": 1317277484, "time": "02:24:44", "date": "11-09-29", "id": "4e840f2c11fb9c8d10000013"}, {"name": "DG", "zip": "78258", "created": 1317277450, "time": "02:24:10", "date": "11-09-29", "id": "4e840f0a2ee8d03f17000014"}, {"name": "MK", "zip": "15001", "created": 1317276118, "time": "02:01:58", "date": "11-09-29", "id": "4e8409d611fb9ce60f000013"}, {"name": "HN", "zip": "74037", "created": 1317276083, "time": "02:01:23", "date": "11-09-29", "id": "4e8409b3b25636a00a00000b"}, {"name": "CC", "zip": "72501", "created": 1317276013, "time": "02:00:13", "date": "11-09-29", "id": "4e84096db25636a20a000023"}, {"name": "CJ", "zip": "91361", "created": 1317274804, "time": "01:40:04", "date": "11-09-29", "id": "4e8404b4709f03ce1b000015"}, {"name": "et", "zip": "99208", "created": 1317274653, "time": "01:37:33", "date": "11-09-29", "id": "4e84041d709f039e1b000011"}, {"name": "AZ", "zip": "", "created": 1317274519, "time": "01:35:19", "date": "11-09-29", "id": "4e840397fb7528630c000011"}, {"name": "PB", "zip": "85719", "created": 1317274445, "time": "01:34:05", "date": "11-09-29", "id": "4e84034dec309e5c1b000012"}, {"name": "JR", "zip": "75154", "created": 1317274275, "time": "01:31:15", "date": "11-09-29", "id": "4e8402a3fb7528650c000015"}, {"name": "TW", "zip": "50613", "created": 1317274195, "time": "01:29:55", "date": "11-09-29", "id": "4e840253709f03ad1b00000f"}, {"name": "SY", "zip": "57110", "created": 1317274065, "time": "01:27:45", "date": "11-09-29", "id": "4e8401d14bd504161d000017"}, {"name": "SS", "zip": "98042-3613", "created": 1317273945, "time": "01:25:45", "date": "11-09-29", "id": "4e84015953b2cf1b07000016"}, {"name": "RH", "zip": "97222", "created": 1317273524, "time": "01:18:44", "date": "11-09-29", "id": "4e83ffb4ec309e991b000011"}, {"name": "CJ", "zip": "82604", "created": 1317273370, "time": "01:16:10", "date": "11-09-29", "id": "4e83ff1a2ee8d04917000012"}, {"name": "LS", "zip": "89509-1859", "created": 1317273314, "time": "01:15:14", "date": "11-09-29", "id": "4e83fee253b2cf1807000019"}, {"name": "BB", "zip": "98661", "created": 1317273305, "time": "01:15:05", "date": "11-09-29", "id": "4e83fed99cd1c1b009000011"}, {"name": "JI", "zip": "60544", "created": 1317273282, "time": "01:14:42", "date": "11-09-29", "id": "4e83fec28d8c374d1500000b"}, {"name": "JK", "zip": "77006-1210", "created": 1317273033, "time": "01:10:33", "date": "11-09-29", "id": "4e83fdc98d8c374515000010"}, {"name": "MM", "zip": "37743", "created": 1317272591, "time": "01:03:11", "date": "11-09-29", "id": "4e83fc0fb25636910a000013"}, {"name": "cs", "zip": "80003", "created": 1317272590, "time": "01:03:10", "date": "11-09-29", "id": "4e83fc0e53b2cf250700000c"}, {"name": "TC", "zip": "40502", "created": 1317272544, "time": "01:02:24", "date": "11-09-29", "id": "4e83fbe02ee8d03f1700000e"}, {"name": "LD", "zip": "46107", "created": 1317272538, "time": "01:02:18", "date": "11-09-29", "id": "4e83fbda53b2cf0b07000012"}, {"name": "MW", "zip": "94086", "created": 1317272218, "time": "00:56:58", "date": "11-09-29", "id": "4e83fa9a709f03b91b000011"}, {"name": "kj", "zip": "80003", "created": 1317272205, "time": "00:56:45", "date": "11-09-29", "id": "4e83fa8db25636860a000015"}, {"name": "JK", "zip": "32053", "created": 1317272197, "time": "00:56:37", "date": "11-09-29", "id": "4e83fa854bd504031d000014"}, {"name": "AH", "zip": "46545", "created": 1317272195, "time": "00:56:35", "date": "11-09-29", "id": "4e83fa8311fb9ce90f00000f"}, {"name": "JA", "zip": "85016", "created": 1317271952, "time": "00:52:32", "date": "11-09-29", "id": "4e83f990709f03ad1b00000c"}, {"name": "AW", "zip": "44314", "created": 1317271774, "time": "00:49:34", "date": "11-09-29", "id": "4e83f8deb25636840a000011"}, {"name": "AS", "zip": "02116", "created": 1317271661, "time": "00:47:41", "date": "11-09-29", "id": "4e83f86d4bd504041d000010"}, {"name": "RC", "zip": "77840", "created": 1317271595, "time": "00:46:35", "date": "11-09-29", "id": "4e83f82b2ee8d0481700000d"}, {"name": "MG", "zip": "71104", "created": 1317271205, "time": "00:40:05", "date": "11-09-29", "id": "4e83f6a511fb9ce70f000012"}, {"name": "SP", "zip": "14620", "created": 1317270956, "time": "00:35:56", "date": "11-09-29", "id": "4e83f5acec309e971b00000f"}, {"name": "mk", "zip": "49043", "created": 1317270737, "time": "00:32:17", "date": "11-09-29", "id": "4e83f4d19cd1c1ae0900000e"}, {"name": "PC", "zip": "90805", "created": 1317270656, "time": "00:30:56", "date": "11-09-29", "id": "4e83f4804bd504251d00000c"}, {"name": "AC", "zip": "12970", "created": 1317270646, "time": "00:30:46", "date": "11-09-29", "id": "4e83f4762ee8d0581700000e"}, {"name": "vc", "zip": "14450", "created": 1317270645, "time": "00:30:45", "date": "11-09-29", "id": "4e83f47553b2cf200700000e"}, {"name": "BD", "zip": "93453", "created": 1317270459, "time": "00:27:39", "date": "11-09-29", "id": "4e83f3bb4bd504281d00000c"}, {"name": "CB", "zip": "", "created": 1317270323, "time": "00:25:23", "date": "11-09-29", "id": "4e83f33311fb9cdd0f000008"}, {"name": "SG", "zip": "54935", "created": 1317270302, "time": "00:25:02", "date": "11-09-29", "id": "4e83f31e2ee8d0491700000f"}, {"name": "MB", "zip": "82601", "created": 1317270278, "time": "00:24:38", "date": "11-09-29", "id": "4e83f3062ee8d0071a00000b"}, {"name": "TG", "zip": "11968", "created": 1317269696, "time": "00:14:56", "date": "11-09-29", "id": "4e83f0c0cf436a4f1f00000a"}, {"name": "BW", "zip": "30033", "created": 1317269651, "time": "00:14:11", "date": "11-09-29", "id": "4e83f093b25636ef1600000e"}, {"name": "MM", "zip": "95829", "created": 1317269610, "time": "00:13:30", "date": "11-09-29", "id": "4e83f06a2ee8d0421700000d"}, {"name": "jg", "zip": "44224", "created": 1317269607, "time": "00:13:27", "date": "11-09-29", "id": "4e83f067ec309e151c000011"}, {"name": "SM", "zip": "17901", "created": 1317269606, "time": "00:13:26", "date": "11-09-29", "id": "4e83f066cf436ae80900000a"}, {"name": "TJ", "zip": "30312", "created": 1317269536, "time": "00:12:16", "date": "11-09-29", "id": "4e83f020cf436af309000014"}, {"name": "CO", "zip": "30047", "created": 1317269499, "time": "00:11:39", "date": "11-09-29", "id": "4e83effbcf436af20900000b"}, {"name": "DP", "zip": "95112", "created": 1317269147, "time": "00:05:47", "date": "11-09-29", "id": "4e83ee9b11fb9c251100000b"}, {"name": "TR", "zip": "89101", "created": 1317269117, "time": "00:05:17", "date": "11-09-29", "id": "4e83ee7d11fb9ce40f000011"}, {"name": "RG", "zip": "60302", "created": 1317269015, "time": "00:03:35", "date": "11-09-29", "id": "4e83ee178d8c374e15000010"}, {"name": "MG", "zip": "27616", "created": 1317268942, "time": "00:02:22", "date": "11-09-29", "id": "4e83edce2ee8d04b17000009"}]