[{"name": "VM", "zip": "55411", "created": 1324008436, "time": "23:07:16", "date": "11-12-15", "id": "4eeac3f44cce277159000012"}, {"name": "PS", "zip": "53214", "created": 1324008015, "time": "23:00:15", "date": "11-12-15", "id": "4eeac24fab728ecb2100006b"}, {"name": "AS", "zip": "", "created": 1324005418, "time": "22:16:58", "date": "11-12-15", "id": "4eeab82a270429084c00000e"}, {"name": "CK", "zip": "33020", "created": 1324005359, "time": "22:15:59", "date": "11-12-15", "id": "4eeab7efab728e847d000022"}, {"name": "PK", "zip": "11772", "created": 1324003091, "time": "21:38:11", "date": "11-12-15", "id": "4eeaaf130a17f54925000003"}, {"name": "cs", "zip": "93405", "created": 1324002759, "time": "21:32:39", "date": "11-12-15", "id": "4eeaadc7ab728e7b7c000024"}, {"name": "KW", "zip": "80112", "created": 1324002570, "time": "21:29:30", "date": "11-12-15", "id": "4eeaad0a4cce27dc50000007"}, {"name": "AK", "zip": "97202", "created": 1324001455, "time": "21:10:55", "date": "11-12-15", "id": "4eeaa8afc85fc2663e00001e"}, {"name": "AT", "zip": "98226", "created": 1324000957, "time": "21:02:37", "date": "11-12-15", "id": "4eeaa6bd4cce27dc50000001"}, {"name": "eb", "zip": "90068", "created": 1323997750, "time": "20:09:10", "date": "11-12-15", "id": "4eea9a36270429780a000032"}, {"name": "sk", "zip": "95126", "created": 1323996122, "time": "19:42:02", "date": "11-12-15", "id": "4eea93daab728e4b32000037"}, {"name": "LJ", "zip": "91504", "created": 1323995509, "time": "19:31:49", "date": "11-12-15", "id": "4eea917569bb5b4d43000066"}, {"name": "AL", "zip": "94105", "created": 1323994934, "time": "19:22:14", "date": "11-12-15", "id": "4eea8f362704291d1800006f"}, {"name": "at", "zip": "02048", "created": 1323994004, "time": "19:06:44", "date": "11-12-15", "id": "4eea8b94c85fc2173300001a"}, {"name": "JR", "zip": "", "created": 1323993972, "time": "19:06:12", "date": "11-12-15", "id": "4eea8b740a17f5e62a000061"}, {"name": "QV", "zip": "90710", "created": 1323993531, "time": "18:58:51", "date": "11-12-15", "id": "4eea89bb0a17f54028000066"}, {"name": "TM", "zip": "30080", "created": 1323993070, "time": "18:51:10", "date": "11-12-15", "id": "4eea87ee270429a36c000072"}, {"name": "PA", "zip": "33510", "created": 1323993005, "time": "18:50:05", "date": "11-12-15", "id": "4eea87ad69bb5bf13900001a"}, {"name": "RP", "zip": "91304", "created": 1323990067, "time": "18:01:07", "date": "11-12-15", "id": "4eea7c33c85fc2625000005d"}, {"name": "RM", "zip": "85248", "created": 1323988719, "time": "17:38:39", "date": "11-12-15", "id": "4eea76ef2704292b73000060"}, {"name": "JH", "zip": "22193", "created": 1323988115, "time": "17:28:35", "date": "11-12-15", "id": "4eea74930a17f5e62a000055"}, {"name": "NC", "zip": "80260", "created": 1323986512, "time": "17:01:52", "date": "11-12-15", "id": "4eea6e504cce276a0b00004e"}, {"name": "EW", "zip": "60417", "created": 1323985757, "time": "16:49:17", "date": "11-12-15", "id": "4eea6b5dab728e184a00005b"}, {"name": "BB", "zip": "92808", "created": 1323984702, "time": "16:31:42", "date": "11-12-15", "id": "4eea673e69bb5b4d43000053"}, {"name": "JP", "zip": "73069", "created": 1323983564, "time": "16:12:44", "date": "11-12-15", "id": "4eea62cc4cce277524000056"}, {"name": "DA", "zip": "34113", "created": 1323982974, "time": "16:02:54", "date": "11-12-15", "id": "4eea607e69bb5b7e2c000044"}, {"name": "jk", "zip": "70130", "created": 1323981311, "time": "15:35:11", "date": "11-12-15", "id": "4eea59ff69bb5b0f7400001d"}, {"name": "cw", "zip": "77318", "created": 1323979400, "time": "15:03:20", "date": "11-12-15", "id": "4eea5288c85fc2625000004d"}, {"name": "SK", "zip": "02134", "created": 1323975623, "time": "14:00:23", "date": "11-12-15", "id": "4eea43c7ab728e203b00005c"}, {"name": "BV", "zip": "89074", "created": 1323975248, "time": "13:54:08", "date": "11-12-15", "id": "4eea425069bb5b0f7400000e"}, {"name": "RL", "zip": "", "created": 1323973258, "time": "13:20:58", "date": "11-12-15", "id": "4eea3a8ac85fc25839000011"}, {"name": "WJ", "zip": "45133", "created": 1323971929, "time": "12:58:49", "date": "11-12-15", "id": "4eea35594cce27ea31000017"}, {"name": "CL", "zip": "45414", "created": 1323971747, "time": "12:55:47", "date": "11-12-15", "id": "4eea34a34cce277524000039"}, {"name": "PE", "zip": "98121", "created": 1323970272, "time": "12:31:12", "date": "11-12-15", "id": "4eea2ee0c85fc2f32400005c"}, {"name": "dl", "zip": "06111", "created": 1323970036, "time": "12:27:16", "date": "11-12-15", "id": "4eea2df4270429b66400000a"}, {"name": "PM", "zip": "06111", "created": 1323969387, "time": "12:16:27", "date": "11-12-15", "id": "4eea2b6b4cce27f80a000034"}, {"name": "CH", "zip": "80015", "created": 1323968239, "time": "11:57:19", "date": "11-12-15", "id": "4eea26ef4cce27722300005b"}, {"name": "JR", "zip": "03102", "created": 1323968094, "time": "11:54:54", "date": "11-12-15", "id": "4eea265ec85fc2f41c00001c"}, {"name": "JG", "zip": "08005", "created": 1323967463, "time": "11:44:23", "date": "11-12-15", "id": "4eea23e7ab728e253c000038"}, {"name": "BM", "zip": "50266", "created": 1323965521, "time": "11:12:01", "date": "11-12-15", "id": "4eea1c514cce270d08000062"}, {"name": "RM", "zip": "87114", "created": 1323965150, "time": "11:05:50", "date": "11-12-15", "id": "4eea1ade0a17f5032f000049"}, {"name": "TB", "zip": "06410", "created": 1323964744, "time": "10:59:04", "date": "11-12-15", "id": "4eea194869bb5b791000002e"}, {"name": "PL", "zip": "80222", "created": 1323964406, "time": "10:53:26", "date": "11-12-15", "id": "4eea17f60a17f5a428000021"}, {"name": "VM", "zip": "94710", "created": 1323964203, "time": "10:50:03", "date": "11-12-15", "id": "4eea172b2704298c0e00005a"}, {"name": "JA", "zip": "73069", "created": 1323963764, "time": "10:42:44", "date": "11-12-15", "id": "4eea1574c85fc25933000049"}, {"name": "JM", "zip": "21613", "created": 1323961553, "time": "10:05:53", "date": "11-12-15", "id": "4eea0cd14cce276a0b000026"}, {"name": "JR", "zip": "46226", "created": 1323961081, "time": "09:58:01", "date": "11-12-15", "id": "4eea0af92704297d6e000040"}, {"name": "jr", "zip": "60015", "created": 1323960560, "time": "09:49:20", "date": "11-12-15", "id": "4eea08f0c85fc2ba30000017"}, {"name": "RM", "zip": "80634", "created": 1323958271, "time": "09:11:11", "date": "11-12-15", "id": "4ee9ffff0a17f54a2f000054"}, {"name": "MK", "zip": "45215", "created": 1323951889, "time": "07:24:49", "date": "11-12-15", "id": "4ee9e71169bb5b7e2c000016"}, {"name": "io", "zip": "27603", "created": 1323951180, "time": "07:13:00", "date": "11-12-15", "id": "4ee9e44cc85fc2625000001f"}, {"name": "RE", "zip": "59870", "created": 1323944069, "time": "05:14:29", "date": "11-12-15", "id": "4ee9c885ab728ec742000024"}, {"name": "TC", "zip": "76048", "created": 1323941607, "time": "04:33:27", "date": "11-12-15", "id": "4ee9bee7ab728ea75900005c"}, {"name": "PB", "zip": "50014", "created": 1323934539, "time": "02:35:39", "date": "11-12-15", "id": "4ee9a34b0a17f54028000010"}, {"name": "kp", "zip": "90035", "created": 1323933926, "time": "02:25:26", "date": "11-12-15", "id": "4ee9a0e6c85fc26250000017"}, {"name": "DG", "zip": "60456", "created": 1323931301, "time": "01:41:41", "date": "11-12-15", "id": "4ee996a54cce272a45000056"}, {"name": "WE", "zip": "60622", "created": 1323931121, "time": "01:38:41", "date": "11-12-15", "id": "4ee995f12704291d18000017"}, {"name": "RM", "zip": "80401", "created": 1323929164, "time": "01:06:04", "date": "11-12-15", "id": "4ee98e4c2704297d6e000019"}, {"name": "RM", "zip": "45241", "created": 1323926841, "time": "00:27:21", "date": "11-12-15", "id": "4ee985392704297d6e000017"}]