[{"name": "MS", "zip": "37932", "created": 1319935353, "time": "20:42:33", "date": "11-10-29", "id": "4eac9d799cd1c1085c000003"}, {"name": "AW", "zip": "70003", "created": 1319931285, "time": "19:34:45", "date": "11-10-29", "id": "4eac8d95b25636ac0c000073"}, {"name": "MN", "zip": "94043", "created": 1319922404, "time": "17:06:44", "date": "11-10-29", "id": "4eac6ae4cf436a4858000067"}, {"name": "MM", "zip": "40206", "created": 1319905927, "time": "12:32:07", "date": "11-10-29", "id": "4eac2a87cf436a4a5800002d"}, {"name": "DW", "zip": "94928", "created": 1319901711, "time": "11:21:51", "date": "11-10-29", "id": "4eac1a0f11fb9c265800002e"}]